[{"id":"0N2AVTrP29G1f4p1eMmp","text":"Hz. Muhammed (sav) doğduktan sonra ilk sütanneliğini kısa bir süre kim yapmıştır?","type":"Çoktan Seçmeli","difficulty":"Kolay","options":["Halime","Amine","Süveybe","Şeyma"],"correctAnswer":"Süveybe","classId":"2bn7xp3tBzOZZG6kHyXP","className":"6","courseId":"r5TWTCIlp018sP37lPL3","unitId":"Hkzo15hb37oOcwf2WDHq","topicId":"nrV3kdiYM7TKs46bppjl","topicName":"2.Hz. Muhammed’in (sav) Ailesi ve Çocukluğu","topic":"2.Hz. Muhammed’in (sav) Ailesi ve Çocukluğu","createdAt":"2026-01-03T09:22:47.397Z"},{"id":"2en4sFRDoDPa8hgoDXOG","text":"Hz. Muhammed (sav) sekiz yaşındayken vefat eden dedesi Abdülmuttalib, onu kime emanet etmiştir?","type":"Çoktan Seçmeli","difficulty":"Orta","options":["Annesi Amine'ye","Amcası Ebu Talib'e","Sütannesi Halime'ye","Amcası Hz. Hamza'ya"],"correctAnswer":"Amcası Ebu Talib'e","classId":"2bn7xp3tBzOZZG6kHyXP","className":"6","courseId":"r5TWTCIlp018sP37lPL3","unitId":"Hkzo15hb37oOcwf2WDHq","topicId":"nrV3kdiYM7TKs46bppjl","topicName":"2.Hz. Muhammed’in (sav) Ailesi ve Çocukluğu","topic":"2.Hz. Muhammed’in (sav) Ailesi ve Çocukluğu","createdAt":"2026-01-03T09:22:47.397Z"},{"id":"2j9ceD7EGglzNVeFR0fT","text":"Mekkeli aileler yeni doğan bebeklerini neden sütanneye verirlerdi?","type":"Çoktan Seçmeli","difficulty":"Zor","options":["Şehirde iş yoğunluğu olduğu için","Bölgenin sağlıklı havasında büyümeleri ve Arapçayı akıcı konuşmaları için","Sadece zengin ailelerin bir geleneği olduğu için","Çocukların daha erken yaşta bağımsız olmaları için"],"correctAnswer":"Bölgenin sağlıklı havasında büyümeleri ve Arapçayı akıcı konuşmaları için","classId":"2bn7xp3tBzOZZG6kHyXP","className":"6","courseId":"r5TWTCIlp018sP37lPL3","unitId":"Hkzo15hb37oOcwf2WDHq","topicId":"nrV3kdiYM7TKs46bppjl","topicName":"2.Hz. Muhammed’in (sav) Ailesi ve Çocukluğu","topic":"2.Hz. Muhammed’in (sav) Ailesi ve Çocukluğu","createdAt":"2026-01-03T09:22:47.397Z"},{"id":"5JZEXFuEWKoYSLc7CdOW","text":"Hz. Muhammed'in (sav) babası Kureyş kabilesinin Haşimoğulları kolundan iken, annesi Amine aynı kabilenin hangi kolundandı?","type":"Çoktan Seçmeli","difficulty":"Zor","options":["Ümeyyeoğulları","Mahzumoğulları","Zühreoğulları","Adioğulları"],"correctAnswer":"Zühreoğulları","classId":"2bn7xp3tBzOZZG6kHyXP","className":"6","courseId":"r5TWTCIlp018sP37lPL3","unitId":"Hkzo15hb37oOcwf2WDHq","topicId":"nrV3kdiYM7TKs46bppjl","topicName":"2.Hz. Muhammed’in (sav) Ailesi ve Çocukluğu","topic":"2.Hz. Muhammed’in (sav) Ailesi ve Çocukluğu","createdAt":"2026-01-03T09:22:47.397Z"},{"id":"7CGkDaGGkSPf9m20lhLI","text":"Hz. Muhammed'in (sav) soyu, Hz. İbrahim'in oğlu _______'e dayanmaktadır.","type":"Boşluk Doldurma","difficulty":"Zor","options":["Hz. Musa","Hz. Yusuf","Hz. İsmail","Hz. İshak"],"correctAnswer":"Hz. İsmail","classId":"2bn7xp3tBzOZZG6kHyXP","className":"6","courseId":"r5TWTCIlp018sP37lPL3","unitId":"Hkzo15hb37oOcwf2WDHq","topicId":"nrV3kdiYM7TKs46bppjl","topicName":"2.Hz. Muhammed’in (sav) Ailesi ve Çocukluğu","topic":"2.Hz. Muhammed’in (sav) Ailesi ve Çocukluğu","createdAt":"2026-01-03T09:22:47.397Z"},{"id":"81hMt06xLu7Xl2JpY17A","text":"Mekkeli aileler yeni doğan bebeklerini, bölgenin sağlıklı havasında büyümeleri ve _______ akıcı bir şekilde konuşmaları için sütanneye verirlerdi.","type":"Boşluk Doldurma","difficulty":"Zor","options":["İbraniceyi","Süryaniceyi","Yunancayı","Arapçayı"],"correctAnswer":"Arapçayı","classId":"2bn7xp3tBzOZZG6kHyXP","className":"6","courseId":"r5TWTCIlp018sP37lPL3","unitId":"Hkzo15hb37oOcwf2WDHq","topicId":"nrV3kdiYM7TKs46bppjl","topicName":"2.Hz. Muhammed’in (sav) Ailesi ve Çocukluğu","topic":"2.Hz. Muhammed’in (sav) Ailesi ve Çocukluğu","createdAt":"2026-01-03T09:22:47.397Z"},{"id":"AKQ8SU4WodpOAJovnNsX","text":"Hz. Muhammed'in (sav) dedesi kimdir?","type":"Çoktan Seçmeli","difficulty":"Kolay","options":["Ebu Talib","Abdullah","Abdülmuttalib","Vehb"],"correctAnswer":"Abdülmuttalib","classId":"2bn7xp3tBzOZZG6kHyXP","className":"6","courseId":"r5TWTCIlp018sP37lPL3","unitId":"Hkzo15hb37oOcwf2WDHq","topicId":"nrV3kdiYM7TKs46bppjl","topicName":"2.Hz. Muhammed’in (sav) Ailesi ve Çocukluğu","topic":"2.Hz. Muhammed’in (sav) Ailesi ve Çocukluğu","createdAt":"2026-01-03T09:22:47.397Z"},{"id":"BvddmMzjIa7Ts3QeT0Ky","text":"Hz. Muhammed (sav) altı yaşındayken annesiyle birlikte babasının kabrini ve Medine'deki akrabalarını ziyaret etmiştir.","type":"Doğru/Yanlış","difficulty":"Zor","options":[],"correctAnswer":"Doğru","classId":"2bn7xp3tBzOZZG6kHyXP","className":"6","courseId":"r5TWTCIlp018sP37lPL3","unitId":"Hkzo15hb37oOcwf2WDHq","topicId":"nrV3kdiYM7TKs46bppjl","topicName":"2.Hz. Muhammed’in (sav) Ailesi ve Çocukluğu","topic":"2.Hz. Muhammed’in (sav) Ailesi ve Çocukluğu","createdAt":"2026-01-03T09:22:47.397Z"},{"id":"C9F5occfBvTtGekL2IMt","text":"Hz. Muhammed'in (sav) dedesi Abdülmuttalib, Kureyş kabilesinin reisiydi.","type":"Doğru/Yanlış","difficulty":"Orta","options":[],"correctAnswer":"Doğru","classId":"2bn7xp3tBzOZZG6kHyXP","className":"6","courseId":"r5TWTCIlp018sP37lPL3","unitId":"Hkzo15hb37oOcwf2WDHq","topicId":"nrV3kdiYM7TKs46bppjl","topicName":"2.Hz. Muhammed’in (sav) Ailesi ve Çocukluğu","topic":"2.Hz. Muhammed’in (sav) Ailesi ve Çocukluğu","createdAt":"2026-01-03T09:22:47.397Z"},{"id":"CAVPSjd5J54ZRmkFboRz","text":"Sütanne geleneğinde çocuklar genellikle dört yaşına kadar sütannelerinde kalırdı.","type":"Doğru/Yanlış","difficulty":"Zor","options":[],"correctAnswer":"Yanlış","classId":"2bn7xp3tBzOZZG6kHyXP","className":"6","courseId":"r5TWTCIlp018sP37lPL3","unitId":"Hkzo15hb37oOcwf2WDHq","topicId":"nrV3kdiYM7TKs46bppjl","topicName":"2.Hz. Muhammed’in (sav) Ailesi ve Çocukluğu","topic":"2.Hz. Muhammed’in (sav) Ailesi ve Çocukluğu","createdAt":"2026-01-03T09:22:47.397Z"},{"id":"Cvxedi8dOpB1RqJDaRpa","text":"Hz. Muhammed'in (sav) dedesi _______, Kureyş kabilesinin reisiydi.","type":"Boşluk Doldurma","difficulty":"Kolay","options":["Ebu Talib","Vehb","Abdülmuttalib","Abdullah"],"correctAnswer":"Abdülmuttalib","classId":"2bn7xp3tBzOZZG6kHyXP","className":"6","courseId":"r5TWTCIlp018sP37lPL3","unitId":"Hkzo15hb37oOcwf2WDHq","topicId":"nrV3kdiYM7TKs46bppjl","topicName":"2.Hz. Muhammed’in (sav) Ailesi ve Çocukluğu","topic":"2.Hz. Muhammed’in (sav) Ailesi ve Çocukluğu","createdAt":"2026-01-03T09:22:47.397Z"},{"id":"F5lzGcoboQs590UKY00A","text":"Hz. Muhammed'in (sav) babasının adı _______'dır.","type":"Boşluk Doldurma","difficulty":"Kolay","options":["Ebu Talib","Hamza","Abdullah","Abbas"],"correctAnswer":"Abdullah","classId":"2bn7xp3tBzOZZG6kHyXP","className":"6","courseId":"r5TWTCIlp018sP37lPL3","unitId":"Hkzo15hb37oOcwf2WDHq","topicId":"nrV3kdiYM7TKs46bppjl","topicName":"2.Hz. Muhammed’in (sav) Ailesi ve Çocukluğu","topic":"2.Hz. Muhammed’in (sav) Ailesi ve Çocukluğu","createdAt":"2026-01-03T09:22:47.397Z"},{"id":"H4ORMl1nTJvsXFB3XbVm","text":"Hz. Muhammed (sav) çocukluğunda dedesi Abdülmuttalib'in yanında kalmıştır.","type":"Doğru/Yanlış","difficulty":"Kolay","options":[],"correctAnswer":"Doğru","classId":"2bn7xp3tBzOZZG6kHyXP","className":"6","courseId":"r5TWTCIlp018sP37lPL3","unitId":"Hkzo15hb37oOcwf2WDHq","topicId":"nrV3kdiYM7TKs46bppjl","topicName":"2.Hz. Muhammed’in (sav) Ailesi ve Çocukluğu","topic":"2.Hz. Muhammed’in (sav) Ailesi ve Çocukluğu","createdAt":"2026-01-03T09:22:47.397Z"},{"id":"HPs71M22U8nY4n3S5MUn","text":"Hz. Muhammed (sav) altı yaşındayken annesi Amine _______ köyünde vefat etmiştir.","type":"Boşluk Doldurma","difficulty":"Orta","options":["Kuba","Ebva","Uhud","Hayber"],"correctAnswer":"Ebva","classId":"2bn7xp3tBzOZZG6kHyXP","className":"6","courseId":"r5TWTCIlp018sP37lPL3","unitId":"Hkzo15hb37oOcwf2WDHq","topicId":"nrV3kdiYM7TKs46bppjl","topicName":"2.Hz. Muhammed’in (sav) Ailesi ve Çocukluğu","topic":"2.Hz. Muhammed’in (sav) Ailesi ve Çocukluğu","createdAt":"2026-01-03T09:22:47.397Z"},{"id":"HwmyjxSwVw7cpjBujtIp","text":"Hz. Muhammed'in (sav) babası Abdullah, ticaret için çıktığı yolculuktan dönerken hangi şehirde vefat etmiştir?","type":"Çoktan Seçmeli","difficulty":"Orta","options":["Mekke","Şam","Medine","Taif"],"correctAnswer":"Medine","classId":"2bn7xp3tBzOZZG6kHyXP","className":"6","courseId":"r5TWTCIlp018sP37lPL3","unitId":"Hkzo15hb37oOcwf2WDHq","topicId":"nrV3kdiYM7TKs46bppjl","topicName":"2.Hz. Muhammed’in (sav) Ailesi ve Çocukluğu","topic":"2.Hz. Muhammed’in (sav) Ailesi ve Çocukluğu","createdAt":"2026-01-03T09:22:47.397Z"},{"id":"IRhsL5g9LO9Qru2hph06","text":"Hz. Muhammed'in (sav) annesi Amine, Kureyş kabilesinin Haşimoğulları kolundandı.","type":"Doğru/Yanlış","difficulty":"Zor","options":[],"correctAnswer":"Yanlış","classId":"2bn7xp3tBzOZZG6kHyXP","className":"6","courseId":"r5TWTCIlp018sP37lPL3","unitId":"Hkzo15hb37oOcwf2WDHq","topicId":"nrV3kdiYM7TKs46bppjl","topicName":"2.Hz. Muhammed’in (sav) Ailesi ve Çocukluğu","topic":"2.Hz. Muhammed’in (sav) Ailesi ve Çocukluğu","createdAt":"2026-01-03T09:22:47.397Z"},{"id":"N41tQbJr9Vsa3MusEVuw","text":"Hz. Muhammed'in (sav) annesinin adı nedir?","type":"Çoktan Seçmeli","difficulty":"Kolay","options":["Fatıma","Hatice","Amine","Zeynep"],"correctAnswer":"Amine","classId":"2bn7xp3tBzOZZG6kHyXP","className":"6","courseId":"r5TWTCIlp018sP37lPL3","unitId":"Hkzo15hb37oOcwf2WDHq","topicId":"nrV3kdiYM7TKs46bppjl","topicName":"2.Hz. Muhammed’in (sav) Ailesi ve Çocukluğu","topic":"2.Hz. Muhammed’in (sav) Ailesi ve Çocukluğu","createdAt":"2026-01-03T09:22:47.397Z"},{"id":"O0zEF36ZLJEASd97lIph","text":"Hz. Muhammed (sav) amcası Ebu Talib'in yanında kaldığı dönemde ona yardımcı olmak amacıyla hangi işleri yapmıştır?","type":"Çoktan Seçmeli","difficulty":"Zor","options":["Marangozluk ve demircilik","Çobanlık ve ticaret seyahatlerine katılma","Çiftçilik ve kuyuculuk","Dokumacılık ve taşımacılık"],"correctAnswer":"Çobanlık ve ticaret seyahatlerine katılma","classId":"2bn7xp3tBzOZZG6kHyXP","className":"6","courseId":"r5TWTCIlp018sP37lPL3","unitId":"Hkzo15hb37oOcwf2WDHq","topicId":"nrV3kdiYM7TKs46bppjl","topicName":"2.Hz. Muhammed’in (sav) Ailesi ve Çocukluğu","topic":"2.Hz. Muhammed’in (sav) Ailesi ve Çocukluğu","createdAt":"2026-01-03T09:22:47.397Z"},{"id":"Ot7O0vXizf4u7SLGV8E9","text":"Hz. Muhammed'in (sav) babası Abdullah, ticaret için çıktığı yolculuk dönüşünde _______'de vefat etmiştir.","type":"Boşluk Doldurma","difficulty":"Orta","options":["Mekke","Medine","Şam","Taif"],"correctAnswer":"Medine","classId":"2bn7xp3tBzOZZG6kHyXP","className":"6","courseId":"r5TWTCIlp018sP37lPL3","unitId":"Hkzo15hb37oOcwf2WDHq","topicId":"nrV3kdiYM7TKs46bppjl","topicName":"2.Hz. Muhammed’in (sav) Ailesi ve Çocukluğu","topic":"2.Hz. Muhammed’in (sav) Ailesi ve Çocukluğu","createdAt":"2026-01-03T09:22:47.397Z"},{"id":"SqZfRJj6loPszaO8L5Ch","text":"Hz. Muhammed (sav) Medine ziyaretinde _______ öğrenmiştir.","type":"Boşluk Doldurma","difficulty":"Zor","options":["Okuma yazmayı","Ticaret yapmayı","Yüzmeyi","Ata binmeyi"],"correctAnswer":"Yüzmeyi","classId":"2bn7xp3tBzOZZG6kHyXP","className":"6","courseId":"r5TWTCIlp018sP37lPL3","unitId":"Hkzo15hb37oOcwf2WDHq","topicId":"nrV3kdiYM7TKs46bppjl","topicName":"2.Hz. Muhammed’in (sav) Ailesi ve Çocukluğu","topic":"2.Hz. Muhammed’in (sav) Ailesi ve Çocukluğu","createdAt":"2026-01-03T09:22:47.397Z"},{"id":"UuXphaNT2wREHV3mMkKB","text":"Hz. Muhammed (sav)'in sütannesi Halime'dir.","type":"Doğru/Yanlış","difficulty":"Kolay","options":[],"correctAnswer":"Doğru","classId":"2bn7xp3tBzOZZG6kHyXP","className":"6","courseId":"r5TWTCIlp018sP37lPL3","unitId":"Hkzo15hb37oOcwf2WDHq","topicId":"nrV3kdiYM7TKs46bppjl","topicName":"2.Hz. Muhammed’in (sav) Ailesi ve Çocukluğu","topic":"2.Hz. Muhammed’in (sav) Ailesi ve Çocukluğu","createdAt":"2026-01-03T09:22:47.397Z"},{"id":"V09qeDGbPtlHoREDgKOK","text":"Hz. Muhammed'in (sav) en çok bilinen ismi 'Muhammed' ne anlama gelmektedir?","type":"Çoktan Seçmeli","difficulty":"Kolay","options":["Sevecen","Övgüye değer","Güvenilir","Adil"],"correctAnswer":"Övgüye değer","classId":"2bn7xp3tBzOZZG6kHyXP","className":"6","courseId":"r5TWTCIlp018sP37lPL3","unitId":"Hkzo15hb37oOcwf2WDHq","topicId":"nrV3kdiYM7TKs46bppjl","topicName":"2.Hz. Muhammed’in (sav) Ailesi ve Çocukluğu","topic":"2.Hz. Muhammed’in (sav) Ailesi ve Çocukluğu","createdAt":"2026-01-03T09:22:47.397Z"},{"id":"WiMK9gFEVLbFjT8qfPfV","text":"Hz. Peygamber'in 'seçilmiş' anlamına gelen ismi 'Ahmed'dir.","type":"Doğru/Yanlış","difficulty":"Orta","options":[],"correctAnswer":"Yanlış","classId":"2bn7xp3tBzOZZG6kHyXP","className":"6","courseId":"r5TWTCIlp018sP37lPL3","unitId":"Hkzo15hb37oOcwf2WDHq","topicId":"nrV3kdiYM7TKs46bppjl","topicName":"2.Hz. Muhammed’in (sav) Ailesi ve Çocukluğu","topic":"2.Hz. Muhammed’in (sav) Ailesi ve Çocukluğu","createdAt":"2026-01-03T09:22:47.397Z"},{"id":"XHjYF8g5PECV87vKTYed","text":"Hz. Muhammed (sav) 4 yaşından 6 yaşına kadar annesi Amine'nin yanında kalmıştır.","type":"Doğru/Yanlış","difficulty":"Orta","options":[],"correctAnswer":"Doğru","classId":"2bn7xp3tBzOZZG6kHyXP","className":"6","courseId":"r5TWTCIlp018sP37lPL3","unitId":"Hkzo15hb37oOcwf2WDHq","topicId":"nrV3kdiYM7TKs46bppjl","topicName":"2.Hz. Muhammed’in (sav) Ailesi ve Çocukluğu","topic":"2.Hz. Muhammed’in (sav) Ailesi ve Çocukluğu","createdAt":"2026-01-03T09:22:47.397Z"},{"id":"Y20A8Zao1BTrHD9qh3Si","text":"Hz. Muhammed (sav), amcası Ebu Talib'in yanında yirmi beş yaşına kadar kalmıştır.","type":"Doğru/Yanlış","difficulty":"Orta","options":[],"correctAnswer":"Doğru","classId":"2bn7xp3tBzOZZG6kHyXP","className":"6","courseId":"r5TWTCIlp018sP37lPL3","unitId":"Hkzo15hb37oOcwf2WDHq","topicId":"nrV3kdiYM7TKs46bppjl","topicName":"2.Hz. Muhammed’in (sav) Ailesi ve Çocukluğu","topic":"2.Hz. Muhammed’in (sav) Ailesi ve Çocukluğu","createdAt":"2026-01-03T09:22:47.397Z"},{"id":"YlLJmuKV1DE0ciMhmG42","text":"Hz. Peygamber'in 'Allah'ı (cc) herkesten daha iyi ve daha çok öven, herkesten daha çok övülen' anlamına gelen ismi hangisidir?","type":"Çoktan Seçmeli","difficulty":"Zor","options":["Mustafa","Muhammed","Ahmed","Mahmud"],"correctAnswer":"Ahmed","classId":"2bn7xp3tBzOZZG6kHyXP","className":"6","courseId":"r5TWTCIlp018sP37lPL3","unitId":"Hkzo15hb37oOcwf2WDHq","topicId":"nrV3kdiYM7TKs46bppjl","topicName":"2.Hz. Muhammed’in (sav) Ailesi ve Çocukluğu","topic":"2.Hz. Muhammed’in (sav) Ailesi ve Çocukluğu","createdAt":"2026-01-03T09:22:47.397Z"},{"id":"ZXXxHpTt24px0Sts2zWw","text":"Hz. Muhammed (sav) kaç yılında nerede doğmuştur?","type":"Çoktan Seçmeli","difficulty":"Kolay","options":["571, Mekke","610, Medine","570, Şam","622, Taif"],"correctAnswer":"571, Mekke","classId":"2bn7xp3tBzOZZG6kHyXP","className":"6","courseId":"r5TWTCIlp018sP37lPL3","unitId":"Hkzo15hb37oOcwf2WDHq","topicId":"nrV3kdiYM7TKs46bppjl","topicName":"2.Hz. Muhammed’in (sav) Ailesi ve Çocukluğu","topic":"2.Hz. Muhammed’in (sav) Ailesi ve Çocukluğu","createdAt":"2026-01-03T09:22:47.397Z"},{"id":"bR3RNkKuFuaFhlMZwNk8","text":"Hz. Muhammed'in (sav) annesi Amine, Kureyş kabilesinin _______ kolundandı.","type":"Boşluk Doldurma","difficulty":"Zor","options":["Haşimoğulları","Ümeyyeoğulları","Zühreoğulları","Mahzumoğulları"],"correctAnswer":"Zühreoğulları","classId":"2bn7xp3tBzOZZG6kHyXP","className":"6","courseId":"r5TWTCIlp018sP37lPL3","unitId":"Hkzo15hb37oOcwf2WDHq","topicId":"nrV3kdiYM7TKs46bppjl","topicName":"2.Hz. Muhammed’in (sav) Ailesi ve Çocukluğu","topic":"2.Hz. Muhammed’in (sav) Ailesi ve Çocukluğu","createdAt":"2026-01-03T09:22:47.397Z"},{"id":"bTBiv94ja81iUdHcRtlV","text":"Hz. Muhammed (sav) sekiz yaşındayken vefat eden dedesi Abdülmuttalib, torununu amcası _______'e emanet etmiştir.","type":"Boşluk Doldurma","difficulty":"Orta","options":["Hz. Hamza","Ebu Talib","Hz. Abbas","Zübeyr"],"correctAnswer":"Ebu Talib","classId":"2bn7xp3tBzOZZG6kHyXP","className":"6","courseId":"r5TWTCIlp018sP37lPL3","unitId":"Hkzo15hb37oOcwf2WDHq","topicId":"nrV3kdiYM7TKs46bppjl","topicName":"2.Hz. Muhammed’in (sav) Ailesi ve Çocukluğu","topic":"2.Hz. Muhammed’in (sav) Ailesi ve Çocukluğu","createdAt":"2026-01-03T09:22:47.397Z"},{"id":"coHGPL623xINbv1Wec1C","text":"Hz. Muhammed (sav) çocukluğunun ilk dört yılını _______ yanında geçirmiştir.","type":"Boşluk Doldurma","difficulty":"Orta","options":["Annesi Amine'nin","Dedesi Abdülmuttalib'in","Sütannesi Halime'nin","Amcası Ebu Talib'in"],"correctAnswer":"Sütannesi Halime'nin","classId":"2bn7xp3tBzOZZG6kHyXP","className":"6","courseId":"r5TWTCIlp018sP37lPL3","unitId":"Hkzo15hb37oOcwf2WDHq","topicId":"nrV3kdiYM7TKs46bppjl","topicName":"2.Hz. Muhammed’in (sav) Ailesi ve Çocukluğu","topic":"2.Hz. Muhammed’in (sav) Ailesi ve Çocukluğu","createdAt":"2026-01-03T09:22:47.397Z"},{"id":"dzTOpULFfz0zUfyrt8Ny","text":"Hz. Muhammed'in (sav) annesi Amine, Medine'den Mekke'ye dönerken hangi köyde vefat etmiştir?","type":"Çoktan Seçmeli","difficulty":"Orta","options":["Kuba","Uhud","Ebva","Hayber"],"correctAnswer":"Ebva","classId":"2bn7xp3tBzOZZG6kHyXP","className":"6","courseId":"r5TWTCIlp018sP37lPL3","unitId":"Hkzo15hb37oOcwf2WDHq","topicId":"nrV3kdiYM7TKs46bppjl","topicName":"2.Hz. Muhammed’in (sav) Ailesi ve Çocukluğu","topic":"2.Hz. Muhammed’in (sav) Ailesi ve Çocukluğu","createdAt":"2026-01-03T09:22:47.397Z"},{"id":"gjNaRFy6ZLFRgd2gMTMw","text":"Hz. Muhammed'in (sav) annesinin adı Amine'dir.","type":"Doğru/Yanlış","difficulty":"Kolay","options":[],"correctAnswer":"Doğru","classId":"2bn7xp3tBzOZZG6kHyXP","className":"6","courseId":"r5TWTCIlp018sP37lPL3","unitId":"Hkzo15hb37oOcwf2WDHq","topicId":"nrV3kdiYM7TKs46bppjl","topicName":"2.Hz. Muhammed’in (sav) Ailesi ve Çocukluğu","topic":"2.Hz. Muhammed’in (sav) Ailesi ve Çocukluğu","createdAt":"2026-01-03T09:22:47.397Z"},{"id":"gmD66T6z5WtrpjXpYIFP","text":"Hz. Muhammed (sav) hangi yaş aralığında amcası Ebu Talib'in yanında kalmıştır?","type":"Çoktan Seçmeli","difficulty":"Orta","options":["0-4 yaş","4-6 yaş","6-8 yaş","8-25 yaş"],"correctAnswer":"8-25 yaş","classId":"2bn7xp3tBzOZZG6kHyXP","className":"6","courseId":"r5TWTCIlp018sP37lPL3","unitId":"Hkzo15hb37oOcwf2WDHq","topicId":"nrV3kdiYM7TKs46bppjl","topicName":"2.Hz. Muhammed’in (sav) Ailesi ve Çocukluğu","topic":"2.Hz. Muhammed’in (sav) Ailesi ve Çocukluğu","createdAt":"2026-01-03T09:22:47.397Z"},{"id":"iM0gPri8xzgzoYJLulXQ","text":"Hz. Muhammed'in (sav) babası Abdullah, Şam'da vefat edip oraya defnedilmiştir.","type":"Doğru/Yanlış","difficulty":"Orta","options":[],"correctAnswer":"Yanlış","classId":"2bn7xp3tBzOZZG6kHyXP","className":"6","courseId":"r5TWTCIlp018sP37lPL3","unitId":"Hkzo15hb37oOcwf2WDHq","topicId":"nrV3kdiYM7TKs46bppjl","topicName":"2.Hz. Muhammed’in (sav) Ailesi ve Çocukluğu","topic":"2.Hz. Muhammed’in (sav) Ailesi ve Çocukluğu","createdAt":"2026-01-03T09:22:47.397Z"},{"id":"jx8EslEwXu83JCSiPKQ8","text":"Hz. Muhammed'in (sav) annesi _______'dir.","type":"Boşluk Doldurma","difficulty":"Kolay","options":["Hatice","Fatıma","Ayşe","Amine"],"correctAnswer":"Amine","classId":"2bn7xp3tBzOZZG6kHyXP","className":"6","courseId":"r5TWTCIlp018sP37lPL3","unitId":"Hkzo15hb37oOcwf2WDHq","topicId":"nrV3kdiYM7TKs46bppjl","topicName":"2.Hz. Muhammed’in (sav) Ailesi ve Çocukluğu","topic":"2.Hz. Muhammed’in (sav) Ailesi ve Çocukluğu","createdAt":"2026-01-03T09:22:47.397Z"},{"id":"mNeessNQbQm6UppKCA4d","text":"Hz. Muhammed (sav) miladi takvime göre 20 Nisan 571 tarihinde Medine'de doğmuştur.","type":"Doğru/Yanlış","difficulty":"Kolay","options":[],"correctAnswer":"Yanlış","classId":"2bn7xp3tBzOZZG6kHyXP","className":"6","courseId":"r5TWTCIlp018sP37lPL3","unitId":"Hkzo15hb37oOcwf2WDHq","topicId":"nrV3kdiYM7TKs46bppjl","topicName":"2.Hz. Muhammed’in (sav) Ailesi ve Çocukluğu","topic":"2.Hz. Muhammed’in (sav) Ailesi ve Çocukluğu","createdAt":"2026-01-03T09:22:47.397Z"},{"id":"oCZPD2e96JOHR3OetTVs","text":"Hz. Muhammed (sav) kaç yaşına kadar sütannesi Halime'nin yanında kalmıştır?","type":"Çoktan Seçmeli","difficulty":"Orta","options":["2","4","6","8"],"correctAnswer":"4","classId":"2bn7xp3tBzOZZG6kHyXP","className":"6","courseId":"r5TWTCIlp018sP37lPL3","unitId":"Hkzo15hb37oOcwf2WDHq","topicId":"nrV3kdiYM7TKs46bppjl","topicName":"2.Hz. Muhammed’in (sav) Ailesi ve Çocukluğu","topic":"2.Hz. Muhammed’in (sav) Ailesi ve Çocukluğu","createdAt":"2026-01-03T09:22:47.397Z"},{"id":"ovTYQxipPBt3tkuUn8Jk","text":"Hz. Muhammed (sav) miladi takvime göre 20 Nisan 571 tarihinde _______'de dünyaya geldi.","type":"Boşluk Doldurma","difficulty":"Kolay","options":["Medine","Şam","Kudüs","Mekke"],"correctAnswer":"Mekke","classId":"2bn7xp3tBzOZZG6kHyXP","className":"6","courseId":"r5TWTCIlp018sP37lPL3","unitId":"Hkzo15hb37oOcwf2WDHq","topicId":"nrV3kdiYM7TKs46bppjl","topicName":"2.Hz. Muhammed’in (sav) Ailesi ve Çocukluğu","topic":"2.Hz. Muhammed’in (sav) Ailesi ve Çocukluğu","createdAt":"2026-01-03T09:22:47.397Z"},{"id":"prxIFmJYjfoluDDyKS6U","text":"Hz. Muhammed'e (sav) doğumunda _______ adı verilmiştir.","type":"Boşluk Doldurma","difficulty":"Kolay","options":["Ahmed","Mustafa","Muhammed","Mahmud"],"correctAnswer":"Muhammed","classId":"2bn7xp3tBzOZZG6kHyXP","className":"6","courseId":"r5TWTCIlp018sP37lPL3","unitId":"Hkzo15hb37oOcwf2WDHq","topicId":"nrV3kdiYM7TKs46bppjl","topicName":"2.Hz. Muhammed’in (sav) Ailesi ve Çocukluğu","topic":"2.Hz. Muhammed’in (sav) Ailesi ve Çocukluğu","createdAt":"2026-01-03T09:22:47.397Z"},{"id":"q24JjrtnU8T22qxlRo6l","text":"Hz. Muhammed (sav) çocukluk yıllarında sadece ticaret yaparak ailesine destek olmuştur.","type":"Doğru/Yanlış","difficulty":"Zor","options":[],"correctAnswer":"Yanlış","classId":"2bn7xp3tBzOZZG6kHyXP","className":"6","courseId":"r5TWTCIlp018sP37lPL3","unitId":"Hkzo15hb37oOcwf2WDHq","topicId":"nrV3kdiYM7TKs46bppjl","topicName":"2.Hz. Muhammed’in (sav) Ailesi ve Çocukluğu","topic":"2.Hz. Muhammed’in (sav) Ailesi ve Çocukluğu","createdAt":"2026-01-03T09:22:47.397Z"},{"id":"sOP77yeCENuZXR7ir20o","text":"Hz. Muhammed (sav), yengesi Fatıma'yı '_______' diyerek anmıştır.","type":"Boşluk Doldurma","difficulty":"Zor","options":["Ailemizin ışığı","İkinci annem","Annemden sonra annem","Yuvamızın direği"],"correctAnswer":"Annemden sonra annem","classId":"2bn7xp3tBzOZZG6kHyXP","className":"6","courseId":"r5TWTCIlp018sP37lPL3","unitId":"Hkzo15hb37oOcwf2WDHq","topicId":"nrV3kdiYM7TKs46bppjl","topicName":"2.Hz. Muhammed’in (sav) Ailesi ve Çocukluğu","topic":"2.Hz. Muhammed’in (sav) Ailesi ve Çocukluğu","createdAt":"2026-01-03T09:22:47.397Z"},{"id":"wEyJbE9WNusyppQ59aWO","text":"Hz. Muhammed (sav) doğduğunda babası Abdullah hayattaydı.","type":"Doğru/Yanlış","difficulty":"Kolay","options":[],"correctAnswer":"Yanlış","classId":"2bn7xp3tBzOZZG6kHyXP","className":"6","courseId":"r5TWTCIlp018sP37lPL3","unitId":"Hkzo15hb37oOcwf2WDHq","topicId":"nrV3kdiYM7TKs46bppjl","topicName":"2.Hz. Muhammed’in (sav) Ailesi ve Çocukluğu","topic":"2.Hz. Muhammed’in (sav) Ailesi ve Çocukluğu","createdAt":"2026-01-03T09:22:47.397Z"},{"id":"wzDYK3Z1lS3A12gaBLbp","text":"Hz. Muhammed'in (sav) soyu, hangi peygamberin oğlu Hz. İsmail'e dayanmaktadır?","type":"Çoktan Seçmeli","difficulty":"Zor","options":["Hz. Musa","Hz. İsa","Hz. İbrahim","Hz. Nuh"],"correctAnswer":"Hz. İbrahim","classId":"2bn7xp3tBzOZZG6kHyXP","className":"6","courseId":"r5TWTCIlp018sP37lPL3","unitId":"Hkzo15hb37oOcwf2WDHq","topicId":"nrV3kdiYM7TKs46bppjl","topicName":"2.Hz. Muhammed’in (sav) Ailesi ve Çocukluğu","topic":"2.Hz. Muhammed’in (sav) Ailesi ve Çocukluğu","createdAt":"2026-01-03T09:22:47.397Z"},{"id":"y67qInIZJg95MbWTLSJ4","text":"Hz. Muhammed'in (sav) sütkardeşleri arasında sadece Şeyma ve Abdullah yer almaktadır.","type":"Doğru/Yanlış","difficulty":"Zor","options":[],"correctAnswer":"Yanlış","classId":"2bn7xp3tBzOZZG6kHyXP","className":"6","courseId":"r5TWTCIlp018sP37lPL3","unitId":"Hkzo15hb37oOcwf2WDHq","topicId":"nrV3kdiYM7TKs46bppjl","topicName":"2.Hz. Muhammed’in (sav) Ailesi ve Çocukluğu","topic":"2.Hz. Muhammed’in (sav) Ailesi ve Çocukluğu","createdAt":"2026-01-03T09:22:47.397Z"},{"id":"yLT8NSGyqqpydSlXcuEm","text":"Hz. Peygamber'in 'Allah'ı (cc) herkesten daha iyi ve daha çok öven' anlamına gelen ismi _______'dir.","type":"Boşluk Doldurma","difficulty":"Orta","options":["Muhammed","Mustafa","Ahmed","Mahmud"],"correctAnswer":"Ahmed","classId":"2bn7xp3tBzOZZG6kHyXP","className":"6","courseId":"r5TWTCIlp018sP37lPL3","unitId":"Hkzo15hb37oOcwf2WDHq","topicId":"nrV3kdiYM7TKs46bppjl","topicName":"2.Hz. Muhammed’in (sav) Ailesi ve Çocukluğu","topic":"2.Hz. Muhammed’in (sav) Ailesi ve Çocukluğu","createdAt":"2026-01-03T09:22:47.397Z"}]