[{"id":"0jxfd9oMjir0fxRv5A1g","unitId":"C0M499utiLGh647x2cnp","topicId":"T326A9OOHtWd4mU6bN2r","courseId":"XboyC5jGWhYxh8RHYtrC","type":"concept","content":{"text":"Kasım"},"createdAt":"2025-09-21T17:00:19.786Z"},{"id":"1AA8PE4Gy8s4Y9Xbot8f","content":{"text":"Gizli Davet"},"courseId":"XboyC5jGWhYxh8RHYtrC","topicId":"6FQTyaJFs3bjPjAa2OwO","unitId":"C0M499utiLGh647x2cnp","type":"concept","createdAt":"2025-09-22T12:03:36.218Z"},{"id":"1Xovnu3I7gDAZnJwv9AW","topicId":"SOxu0mWeXh96N3t9qo6a","courseId":"XboyC5jGWhYxh8RHYtrC","unitId":"C0M499utiLGh647x2cnp","content":{"text":"Peygamberimiz 63 yaşında 632 yılında Medine'de vefat etti."},"type":"sentence","createdAt":"2025-09-28T11:10:02.699Z"},{"id":"1Z8sd8QGhWvxXSrvGNnv","type":"concept","unitId":"C0M499utiLGh647x2cnp","topicId":"6FQTyaJFs3bjPjAa2OwO","courseId":"XboyC5jGWhYxh8RHYtrC","content":{"text":"Tefekkür"},"createdAt":"2025-09-22T12:03:36.218Z"},{"id":"3SS93GC2psOQJIBBh9Kd","content":{"definition":"Lakabı","term":"Muhammedülemin"},"topicId":"T326A9OOHtWd4mU6bN2r","courseId":"XboyC5jGWhYxh8RHYtrC","unitId":"C0M499utiLGh647x2cnp","type":"definition","createdAt":"2025-09-21T17:00:19.786Z"},{"id":"4DOhwybH8KNOBPCv2QwY","courseId":"XboyC5jGWhYxh8RHYtrC","unitId":"C0M499utiLGh647x2cnp","type":"concept","topicId":"6FQTyaJFs3bjPjAa2OwO","content":{"text":"Sahabi"},"createdAt":"2025-09-22T12:03:36.218Z"},{"id":"4Xhb1OC2duG1oLKHQVgq","type":"definition","courseId":"XboyC5jGWhYxh8RHYtrC","unitId":"C0M499utiLGh647x2cnp","content":{"term":"Hudeybiye Antlaşması","definition":"Müşrikler ile yapılan barış anlaşması"},"topicId":"SOxu0mWeXh96N3t9qo6a","createdAt":{"seconds":1759057651,"nanoseconds":875000000}},{"id":"5EXhpY2CiNt9sl0gF7ON","topicId":"6FQTyaJFs3bjPjAa2OwO","unitId":"C0M499utiLGh647x2cnp","content":{"definition":"İlk kıblemiz","term":"Mescid-i Aksa"},"type":"definition","courseId":"XboyC5jGWhYxh8RHYtrC","createdAt":"2025-09-22T12:03:36.218Z"},{"id":"5U0aAEVyfqIuBokOEaNC","courseId":"XboyC5jGWhYxh8RHYtrC","topicId":"T326A9OOHtWd4mU6bN2r","type":"concept","content":{"text":"Fil Vakası"},"unitId":"C0M499utiLGh647x2cnp","createdAt":"2025-09-21T17:00:19.786Z"},{"id":"5VYhCbdCidEbrhXVJ6cN","type":"concept","unitId":"C0M499utiLGh647x2cnp","topicId":"T326A9OOHtWd4mU6bN2r","courseId":"XboyC5jGWhYxh8RHYtrC","content":{"text":"Tahire"},"createdAt":"2025-09-21T17:00:19.786Z"},{"id":"5aqLZEatUa1A5HqylcyQ","type":"concept","unitId":"C0M499utiLGh647x2cnp","topicId":"T326A9OOHtWd4mU6bN2r","content":{"text":"Fâtıma"},"courseId":"XboyC5jGWhYxh8RHYtrC","createdAt":"2025-09-21T17:00:19.786Z"},{"id":"5oE8ID4OzHK8mGrLDJaB","topicId":"6FQTyaJFs3bjPjAa2OwO","unitId":"C0M499utiLGh647x2cnp","type":"sentence","courseId":"XboyC5jGWhYxh8RHYtrC","content":{"text":"İlk günden takva üzerine kurulan mescit (Kuba Mescidi) içinde namaz kılman elbette daha doğrudur."},"createdAt":"2025-09-22T12:03:36.218Z"},{"id":"7PrTkdakxCRyVvGj5LnZ","topicId":"6FQTyaJFs3bjPjAa2OwO","unitId":"C0M499utiLGh647x2cnp","courseId":"XboyC5jGWhYxh8RHYtrC","content":{"definition":"Medineli Müslümanlara denir.","term":"Ensar"},"type":"definition","createdAt":"2025-09-22T12:03:36.218Z"},{"id":"7qqX9rpQRDVBzC7su7C7","courseId":"XboyC5jGWhYxh8RHYtrC","unitId":"C0M499utiLGh647x2cnp","topicId":"T326A9OOHtWd4mU6bN2r","content":{"text":"Ümmü Eymen"},"type":"concept","createdAt":"2025-09-21T17:00:19.786Z"},{"id":"9FWBG2Hx9i1GDqpVWb79","courseId":"XboyC5jGWhYxh8RHYtrC","type":"definition","content":{"term":"Ezan","definition":"Namaz vakitlerini Müslümanlara bildirmek için Bilal-i Habeşi'nin ilk kez okuduğu, ilahi çağrıdır."},"unitId":"C0M499utiLGh647x2cnp","topicId":"SOxu0mWeXh96N3t9qo6a","createdAt":{"seconds":1759056833,"nanoseconds":496000000}},{"id":"9IGbnIIDyGczKHMLzS4n","courseId":"XboyC5jGWhYxh8RHYtrC","topicId":"6FQTyaJFs3bjPjAa2OwO","unitId":"C0M499utiLGh647x2cnp","type":"definition","content":{"definition":"Boykot dönemi 616-619 arası","term":"Ambargo"},"createdAt":"2025-09-22T12:03:36.218Z"},{"id":"AOLs6wUCBhgKgT1AMY1X","courseId":"XboyC5jGWhYxh8RHYtrC","type":"sentence","content":{"text":"Medine'de kıble Mescid-i Aksa'dan Kâbe'ye doğru değiştirildi."},"topicId":"SOxu0mWeXh96N3t9qo6a","unitId":"C0M499utiLGh647x2cnp","createdAt":"2025-09-28T11:10:02.699Z"},{"id":"BST6RiriECci9iww0YON","type":"definition","unitId":"C0M499utiLGh647x2cnp","topicId":"T326A9OOHtWd4mU6bN2r","content":{"definition":"Dedesi","term":"Abdülmuttalib"},"courseId":"XboyC5jGWhYxh8RHYtrC","createdAt":"2025-09-21T17:00:19.786Z"},{"id":"BXouFh9n7NozHnCfaY3X","unitId":"C0M499utiLGh647x2cnp","type":"concept","topicId":"6FQTyaJFs3bjPjAa2OwO","courseId":"XboyC5jGWhYxh8RHYtrC","content":{"text":"Dârülerkam"},"createdAt":"2025-09-22T12:03:36.218Z"},{"id":"BYpwrnBX8Acf8wqjwIC1","content":{"definition":"Hacerülesved’i yerine koyduğu olay","term":"Kâbe Hakemliği"},"unitId":"C0M499utiLGh647x2cnp","topicId":"T326A9OOHtWd4mU6bN2r","type":"definition","courseId":"XboyC5jGWhYxh8RHYtrC","createdAt":"2025-09-21T17:00:19.786Z"},{"id":"BYrQHdaDu2xw62xArLoC","type":"sentence","topicId":"6FQTyaJFs3bjPjAa2OwO","courseId":"XboyC5jGWhYxh8RHYtrC","unitId":"C0M499utiLGh647x2cnp","content":{"text":"Mescid-i Aksa Müslümanların ilk kıblesidir."},"createdAt":"2025-09-22T12:03:36.218Z"},{"id":"Bm4xihnhbDG5OI1mgs1F","unitId":"C0M499utiLGh647x2cnp","content":{"text":"Allah Resulü’nün (sav) 610 yılında Mekke’de başlayan peygamberlik görevi 632’de Medine’de tamamlanmıştır."},"type":"sentence","courseId":"XboyC5jGWhYxh8RHYtrC","topicId":"6FQTyaJFs3bjPjAa2OwO","createdAt":"2025-09-22T12:03:36.218Z"},{"id":"Bo1QRw24VXX8A8zUkjxn","unitId":"C0M499utiLGh647x2cnp","topicId":"T326A9OOHtWd4mU6bN2r","content":{"definition":"Mariye annemizden olan çocuğu","term":"İbrahim"},"courseId":"XboyC5jGWhYxh8RHYtrC","type":"definition","createdAt":"2025-09-21T17:00:19.786Z"},{"id":"D9aAFZl6Tz6idXkWIbOv","unitId":"C0M499utiLGh647x2cnp","type":"concept","topicId":"T326A9OOHtWd4mU6bN2r","content":{"text":"Kureyş"},"courseId":"XboyC5jGWhYxh8RHYtrC","createdAt":"2025-09-21T17:00:19.786Z"},{"id":"DpvkW6I2edQDdtYbMpaF","topicId":"6FQTyaJFs3bjPjAa2OwO","type":"definition","unitId":"C0M499utiLGh647x2cnp","courseId":"XboyC5jGWhYxh8RHYtrC","content":{"definition":"Allah’ın (cc) dilediği emir, hüküm ve bilgileri peygamberine bildirmesidir.","term":"Vahiy"},"createdAt":"2025-09-22T12:03:36.218Z"},{"id":"DwHhkwTdiPkAkKBFnsuF","content":{"term":"Kıble","definition":"Müslümanların namaz kılarken yöneldiği, başlangıçta Mescid-i Aksa olup sonradan Kâbe'ye çevrilen yön."},"type":"definition","topicId":"SOxu0mWeXh96N3t9qo6a","unitId":"C0M499utiLGh647x2cnp","courseId":"XboyC5jGWhYxh8RHYtrC","createdAt":{"seconds":1759056833,"nanoseconds":496000000}},{"id":"EnnJM372dUXYGh2seluZ","courseId":"XboyC5jGWhYxh8RHYtrC","unitId":"C0M499utiLGh647x2cnp","topicId":"6FQTyaJFs3bjPjAa2OwO","content":{"definition":"Allah Resulü’nün (sav) bir gece Kâbe'den Kudüs'teki Mescid-i Aksa'ya Allah'ın (cc) izniyle götürülmesi","term":"İsra"},"type":"definition","createdAt":"2025-09-22T12:03:36.218Z"},{"id":"FA1wZnkpVT1irUTUNhJw","courseId":"XboyC5jGWhYxh8RHYtrC","type":"concept","topicId":"6FQTyaJFs3bjPjAa2OwO","content":{"text":"Vahiy"},"unitId":"C0M499utiLGh647x2cnp","createdAt":"2025-09-22T12:03:36.218Z"},{"id":"FVpmxeTP6KZywBxLwTE0","type":"definition","unitId":"C0M499utiLGh647x2cnp","topicId":"6FQTyaJFs3bjPjAa2OwO","courseId":"XboyC5jGWhYxh8RHYtrC","content":{"term":"Tevhit","definition":"Tek yaratıcı inancı"},"createdAt":"2025-09-22T12:03:36.218Z"},{"id":"FYU6ygjcmadJlgCxckL1","type":"concept","topicId":"T326A9OOHtWd4mU6bN2r","courseId":"XboyC5jGWhYxh8RHYtrC","content":{"text":"Amine"},"unitId":"C0M499utiLGh647x2cnp","createdAt":"2025-09-21T17:00:19.786Z"},{"id":"FsXlSlG86HrVH132Km0C","type":"definition","content":{"term":"Gizli Davet","definition":"610-613 yılları arası dönem"},"topicId":"6FQTyaJFs3bjPjAa2OwO","courseId":"XboyC5jGWhYxh8RHYtrC","unitId":"C0M499utiLGh647x2cnp","createdAt":"2025-09-22T12:03:36.218Z"},{"id":"GmdyESSnQRwBP95x4vI5","topicId":"6FQTyaJFs3bjPjAa2OwO","courseId":"XboyC5jGWhYxh8RHYtrC","type":"definition","content":{"term":"İlk inanlar","definition":"Hz.Hatice, Zeyd bin Harise, Ali, Ebubekir"},"unitId":"C0M499utiLGh647x2cnp","createdAt":"2025-09-22T12:03:36.218Z"},{"id":"HAZbzJf9lKnI1J1l5Kha","type":"concept","content":{"text":"Muhacir"},"topicId":"6FQTyaJFs3bjPjAa2OwO","courseId":"XboyC5jGWhYxh8RHYtrC","unitId":"C0M499utiLGh647x2cnp","createdAt":"2025-09-22T12:03:36.218Z"},{"id":"HNW2AE6Kn7oO8Qd6R37b","topicId":"T326A9OOHtWd4mU6bN2r","type":"definition","courseId":"XboyC5jGWhYxh8RHYtrC","unitId":"C0M499utiLGh647x2cnp","content":{"definition":"Lakabı","term":"el-Emin"},"createdAt":"2025-09-21T17:00:19.786Z"},{"id":"HTjiry7LUoEseoOrg1rp","content":{"definition":"Kabilesi","term":"Kureyş"},"courseId":"XboyC5jGWhYxh8RHYtrC","type":"definition","unitId":"C0M499utiLGh647x2cnp","topicId":"T326A9OOHtWd4mU6bN2r","createdAt":"2025-09-21T17:00:19.786Z"},{"id":"Hi1bUdt77uSZEetuJNu0","content":{"text":"Muhammedülemin"},"topicId":"T326A9OOHtWd4mU6bN2r","unitId":"C0M499utiLGh647x2cnp","type":"concept","courseId":"XboyC5jGWhYxh8RHYtrC","createdAt":"2025-09-21T17:00:19.786Z"},{"id":"HzFyfKRZb8U2GtUvB3u7","type":"sentence","content":{"text":"Endişelenme, Allah bizimledir. Üçüncüleri Allah olan iki kişiye ne yapabilirler."},"topicId":"6FQTyaJFs3bjPjAa2OwO","courseId":"XboyC5jGWhYxh8RHYtrC","unitId":"C0M499utiLGh647x2cnp","createdAt":"2025-09-22T12:03:36.218Z"},{"id":"IdgfxcBvjDkQgmHuSsKH","courseId":"XboyC5jGWhYxh8RHYtrC","topicId":"SOxu0mWeXh96N3t9qo6a","unitId":"C0M499utiLGh647x2cnp","content":{"term":"Ebu Eyyüb el-Ensârî","definition":"Peygamberimizi evinde misafir eden sahabi"},"type":"definition","createdAt":{"seconds":1759057651,"nanoseconds":875000000}},{"id":"Ir3WLgMdngZRe2zkUb4H","courseId":"XboyC5jGWhYxh8RHYtrC","topicId":"T326A9OOHtWd4mU6bN2r","content":{"text":"Hilfülfudul"},"type":"concept","unitId":"C0M499utiLGh647x2cnp","createdAt":"2025-09-21T17:00:19.786Z"},{"id":"JVZdWF3ryuZnW1WZv9dP","courseId":"XboyC5jGWhYxh8RHYtrC","type":"concept","topicId":"T326A9OOHtWd4mU6bN2r","unitId":"C0M499utiLGh647x2cnp","content":{"text":"Rukiye"},"createdAt":"2025-09-21T17:00:19.786Z"},{"id":"K3j5KWwAWT7rcu4ZSAkt","courseId":"XboyC5jGWhYxh8RHYtrC","unitId":"C0M499utiLGh647x2cnp","content":{"term":"Taif","definition":"İslam'ı tebliğ için gittiği şehir"},"topicId":"6FQTyaJFs3bjPjAa2OwO","type":"definition","createdAt":"2025-09-22T12:03:36.218Z"},{"id":"KWq9LoUQke2GpBsQkY4a","courseId":"XboyC5jGWhYxh8RHYtrC","type":"concept","unitId":"C0M499utiLGh647x2cnp","content":{"text":"Hacerülesved"},"topicId":"T326A9OOHtWd4mU6bN2r","createdAt":"2025-09-21T17:00:19.786Z"},{"id":"Knv3dAOMaNVzZIRoKjiD","courseId":"XboyC5jGWhYxh8RHYtrC","content":{"term":"Akabe Biatları","definition":"Medinelilerin müslüman olup peygamberimize söz vermeleri"},"type":"definition","topicId":"6FQTyaJFs3bjPjAa2OwO","unitId":"C0M499utiLGh647x2cnp","createdAt":"2025-09-22T12:03:36.218Z"},{"id":"L9gpHS5ye24SymSIlphy","courseId":"XboyC5jGWhYxh8RHYtrC","type":"concept","topicId":"T326A9OOHtWd4mU6bN2r","unitId":"C0M499utiLGh647x2cnp","content":{"text":"el-Emin"},"createdAt":"2025-09-21T17:00:19.786Z"},{"id":"LOWzHUIjZTOBLkU3QJaV","content":{"text":"İlk inanlar"},"topicId":"6FQTyaJFs3bjPjAa2OwO","type":"concept","courseId":"XboyC5jGWhYxh8RHYtrC","unitId":"C0M499utiLGh647x2cnp","createdAt":"2025-09-22T12:03:36.218Z"},{"id":"LQttN0VZIg7Z0vu9lkAL","type":"definition","content":{"definition":"Çocuğu","term":"Abdullah"},"unitId":"C0M499utiLGh647x2cnp","courseId":"XboyC5jGWhYxh8RHYtrC","topicId":"T326A9OOHtWd4mU6bN2r","createdAt":"2025-09-21T17:00:19.786Z"},{"id":"MDrQMGhfgWkEGvSKvT6f","courseId":"XboyC5jGWhYxh8RHYtrC","topicId":"6FQTyaJFs3bjPjAa2OwO","content":{"text":"Erkam b. Ebi’l-Erkam"},"unitId":"C0M499utiLGh647x2cnp","type":"concept","createdAt":"2025-09-22T12:03:36.218Z"},{"id":"MMbW34AdODv8JVQG2Qe9","unitId":"C0M499utiLGh647x2cnp","courseId":"XboyC5jGWhYxh8RHYtrC","topicId":"6FQTyaJFs3bjPjAa2OwO","content":{"text":"Zeyd b. Hârise"},"type":"concept","createdAt":"2025-09-22T12:03:36.218Z"},{"id":"Muebvh4UlIBAUQqj1ntO","type":"concept","unitId":"C0M499utiLGh647x2cnp","courseId":"XboyC5jGWhYxh8RHYtrC","topicId":"6FQTyaJFs3bjPjAa2OwO","content":{"text":"İnziva"},"createdAt":"2025-09-22T12:03:36.218Z"},{"id":"NQiMQoX5HSvhOy38wmU6","content":{"definition":"Dadısı","term":"Ümmü Eymen"},"type":"definition","topicId":"T326A9OOHtWd4mU6bN2r","courseId":"XboyC5jGWhYxh8RHYtrC","unitId":"C0M499utiLGh647x2cnp","createdAt":"2025-09-21T17:00:19.786Z"},{"id":"NZyxdxHLafxm502yrHM0","topicId":"6FQTyaJFs3bjPjAa2OwO","unitId":"C0M499utiLGh647x2cnp","content":{"definition":"Köşeye çekilme, bir müddet insanlardan uzaklaşma anlamlarına gelmektedir.","term":"İnziva"},"courseId":"XboyC5jGWhYxh8RHYtrC","type":"definition","createdAt":"2025-09-22T12:03:36.218Z"},{"id":"NzeLmWQ9RDAXliWeerhK","unitId":"C0M499utiLGh647x2cnp","type":"definition","topicId":"T326A9OOHtWd4mU6bN2r","content":{"definition":"Hatice annemizin lakabı","term":"Tahire"},"courseId":"XboyC5jGWhYxh8RHYtrC","createdAt":"2025-09-21T17:00:19.786Z"},{"id":"PPRlGnrzIXQIvNNU2OJs","type":"concept","topicId":"T326A9OOHtWd4mU6bN2r","unitId":"C0M499utiLGh647x2cnp","courseId":"XboyC5jGWhYxh8RHYtrC","createdAt":"2025-09-21T17:00:19.786Z","content":{"definition":"","title":"","categories":[],"items":[],"term":"","text":"Süt kardeşleri"}},{"id":"PiiJ32hSSaMlwxcXmHPu","courseId":"XboyC5jGWhYxh8RHYtrC","unitId":"C0M499utiLGh647x2cnp","content":{"text":"Halime"},"type":"concept","topicId":"T326A9OOHtWd4mU6bN2r","createdAt":"2025-09-21T17:00:19.786Z"},{"id":"PnNDnllSkMrMe0KXKTK6","content":{"term":"Fâtıma","definition":"Kendisinden sonra vefat eden tek çocuğu"},"courseId":"XboyC5jGWhYxh8RHYtrC","topicId":"T326A9OOHtWd4mU6bN2r","type":"definition","unitId":"C0M499utiLGh647x2cnp","createdAt":"2025-09-21T17:00:19.786Z"},{"id":"Q3XLiQSbf1awyPARLUzR","content":{"definition":"Peygamberimize iman eden ve onu görmüş kişiler","term":"Sahabi"},"unitId":"C0M499utiLGh647x2cnp","type":"definition","courseId":"XboyC5jGWhYxh8RHYtrC","topicId":"6FQTyaJFs3bjPjAa2OwO","createdAt":"2025-09-22T12:03:36.218Z"},{"id":"QJDcQzW3OunBFl236aCf","content":{"text":"Evlenene kadar yani 25 yaşına kadar amcası Ebu Talib ile yaşadı."},"type":"sentence","courseId":"XboyC5jGWhYxh8RHYtrC","topicId":"T326A9OOHtWd4mU6bN2r","unitId":"C0M499utiLGh647x2cnp","createdAt":"2025-09-21T17:00:19.786Z"},{"id":"SARExBmbn7Wh1SucihVL","content":{"text":"Ravza-i Mutahhara"},"topicId":"SOxu0mWeXh96N3t9qo6a","unitId":"C0M499utiLGh647x2cnp","type":"concept","courseId":"XboyC5jGWhYxh8RHYtrC","createdAt":"2025-09-28T11:07:31.875Z"},{"id":"SETwtxCsAgMpNB5gyivf","content":{"text":"Bila-i Habeşi"},"courseId":"XboyC5jGWhYxh8RHYtrC","type":"concept","unitId":"C0M499utiLGh647x2cnp","topicId":"SOxu0mWeXh96N3t9qo6a","createdAt":"2025-09-28T11:07:31.875Z"},{"id":"SGqBhYe3l9lyNt2j6efz","content":{"text":"Yanında yetiştiği Ebu Talib’e sürülerine çobanlık ederek ve ticari işlerinde yardımcı olarak destek olmaya çalıştı."},"type":"sentence","unitId":"C0M499utiLGh647x2cnp","topicId":"T326A9OOHtWd4mU6bN2r","courseId":"XboyC5jGWhYxh8RHYtrC","createdAt":"2025-09-21T17:00:19.786Z"},{"id":"SQ0VnSFltCjgl6R3onF3","type":"concept","unitId":"C0M499utiLGh647x2cnp","courseId":"XboyC5jGWhYxh8RHYtrC","content":{"text":"Hatice"},"topicId":"T326A9OOHtWd4mU6bN2r","createdAt":"2025-09-21T17:00:19.786Z"},{"id":"SdtyBPZHGfFwjuLBbPxJ","content":{"text":"Uhud Savaşı"},"type":"concept","courseId":"XboyC5jGWhYxh8RHYtrC","topicId":"SOxu0mWeXh96N3t9qo6a","unitId":"C0M499utiLGh647x2cnp","createdAt":"2025-09-28T11:07:31.875Z"},{"id":"TW642kDTWJTYHItyjEzw","content":{"definition":"Eşi hatice ve amcası Ebu Talibin vefat ettiği yıl","term":"Hüzün Yılı"},"topicId":"6FQTyaJFs3bjPjAa2OwO","courseId":"XboyC5jGWhYxh8RHYtrC","type":"definition","unitId":"C0M499utiLGh647x2cnp","createdAt":"2025-09-22T12:03:36.218Z"},{"id":"TYRIflzS9Oyt7gerBDfQ","courseId":"XboyC5jGWhYxh8RHYtrC","type":"concept","topicId":"6FQTyaJFs3bjPjAa2OwO","content":{"text":"İlk Hicret"},"unitId":"C0M499utiLGh647x2cnp","createdAt":"2025-09-22T12:03:36.218Z"},{"id":"TiDLrRsVZfKK0eI6tijK","topicId":"T326A9OOHtWd4mU6bN2r","courseId":"XboyC5jGWhYxh8RHYtrC","unitId":"C0M499utiLGh647x2cnp","type":"concept","content":{"text":"Mekke"},"createdAt":"2025-09-21T17:00:19.786Z"},{"id":"TqXG1thZagPRzMxbqmN6","courseId":"XboyC5jGWhYxh8RHYtrC","topicId":"SOxu0mWeXh96N3t9qo6a","unitId":"C0M499utiLGh647x2cnp","type":"definition","content":{"term":"Muhacir","definition":"İnançları uğruna Mekke'den Medine'ye göç eden, mal ve yurtlarını terk etmiş Müslümanlardır."},"createdAt":{"seconds":1759056833,"nanoseconds":496000000}},{"id":"U8bDXNvkrDwBWblVMtPb","content":{"text":"Kuba Mescidi"},"topicId":"6FQTyaJFs3bjPjAa2OwO","type":"concept","courseId":"XboyC5jGWhYxh8RHYtrC","unitId":"C0M499utiLGh647x2cnp","createdAt":"2025-09-22T12:03:36.218Z"},{"id":"UBS9jDbfpMb4bEWvQpOt","topicId":"6FQTyaJFs3bjPjAa2OwO","unitId":"C0M499utiLGh647x2cnp","content":{"text":"Hüzün Yılı"},"type":"concept","courseId":"XboyC5jGWhYxh8RHYtrC","createdAt":"2025-09-22T12:03:36.218Z"},{"id":"UOfuuKJvGJQmfS1QxbES","content":{"definition":"Medine'de evlendiği annemiz","term":"Mariye"},"topicId":"T326A9OOHtWd4mU6bN2r","unitId":"C0M499utiLGh647x2cnp","courseId":"XboyC5jGWhYxh8RHYtrC","type":"definition","createdAt":"2025-09-21T17:00:19.786Z"},{"id":"UnI941Bu0vEVOQ4z5JcU","topicId":"SOxu0mWeXh96N3t9qo6a","courseId":"XboyC5jGWhYxh8RHYtrC","content":{"text":"Muhacir ve Ensar kardeş ilan edildi. Buna muahat denir."},"type":"sentence","unitId":"C0M499utiLGh647x2cnp","createdAt":"2025-09-28T11:10:02.699Z"},{"id":"V39HprkpT8Bn7KUwL8I4","topicId":"T326A9OOHtWd4mU6bN2r","type":"concept","unitId":"C0M499utiLGh647x2cnp","content":{"text":"Cahiliye"},"courseId":"XboyC5jGWhYxh8RHYtrC","createdAt":"2025-09-21T17:00:19.786Z"},{"id":"VEwP2zACzGK0ZaeJq2as","unitId":"C0M499utiLGh647x2cnp","courseId":"XboyC5jGWhYxh8RHYtrC","type":"concept","content":{"text":"Mariye"},"topicId":"T326A9OOHtWd4mU6bN2r","createdAt":"2025-09-21T17:00:19.786Z"},{"id":"VKRRKHBUbWE6H3SUCZML","courseId":"XboyC5jGWhYxh8RHYtrC","type":"sentence","content":{"text":"Hz.Muhammed (sav) 571 yılı Rebîülevvel ayının 12’sinde Pazartesi günü Mekke’de dünyaya gelmiştir."},"topicId":"T326A9OOHtWd4mU6bN2r","unitId":"C0M499utiLGh647x2cnp","createdAt":"2025-09-21T17:00:19.786Z"},{"id":"VUE8uwhPVXAsyqlDhH5w","courseId":"XboyC5jGWhYxh8RHYtrC","content":{"definition":"İlk mescid-cami","term":"Kuba Mescidi"},"type":"definition","topicId":"6FQTyaJFs3bjPjAa2OwO","unitId":"C0M499utiLGh647x2cnp","createdAt":"2025-09-22T12:03:36.218Z"},{"id":"WEH3nFENSAKjvuqk5uqM","courseId":"XboyC5jGWhYxh8RHYtrC","type":"concept","content":{"text":"Mescid-i Aksa"},"topicId":"6FQTyaJFs3bjPjAa2OwO","unitId":"C0M499utiLGh647x2cnp","createdAt":"2025-09-22T12:03:36.218Z"},{"id":"WMJ1D5GV3Y94l9yDUC0V","type":"concept","topicId":"T326A9OOHtWd4mU6bN2r","courseId":"XboyC5jGWhYxh8RHYtrC","content":{"text":"Abdülmuttalib"},"unitId":"C0M499utiLGh647x2cnp","createdAt":"2025-09-21T17:00:19.786Z"},{"id":"Wc89tV9oOaThLRlsy2En","courseId":"XboyC5jGWhYxh8RHYtrC","unitId":"C0M499utiLGh647x2cnp","topicId":"T326A9OOHtWd4mU6bN2r","type":"definition","createdAt":"2025-09-21T17:00:19.786Z","content":{"categories":[],"title":"","definition":"Abdullah, Şeyma ve Üneyse","term":"Süt kardeşleri","items":[],"text":""}},{"id":"XRMGf05WxF6l3AHGyRXy","courseId":"XboyC5jGWhYxh8RHYtrC","content":{"definition":"Habeşistan","term":"İlk Hicret"},"topicId":"6FQTyaJFs3bjPjAa2OwO","unitId":"C0M499utiLGh647x2cnp","type":"definition","createdAt":"2025-09-22T12:03:36.218Z"},{"id":"XWsiCqDBRZp3tSOiN5xZ","type":"concept","courseId":"XboyC5jGWhYxh8RHYtrC","unitId":"C0M499utiLGh647x2cnp","topicId":"T326A9OOHtWd4mU6bN2r","content":{"text":"Abdullah"},"createdAt":"2025-09-21T17:00:19.786Z"},{"id":"YCZX1uOfa5nX0K4bCltb","content":{"text":"Miraç"},"type":"concept","unitId":"C0M499utiLGh647x2cnp","courseId":"XboyC5jGWhYxh8RHYtrC","topicId":"6FQTyaJFs3bjPjAa2OwO","createdAt":"2025-09-22T12:03:36.218Z"},{"id":"YQ7KcAc1qwJXl8J7yhBi","content":{"definition":"Üçüncü savaş","term":"Hendek Savaşı"},"courseId":"XboyC5jGWhYxh8RHYtrC","type":"definition","topicId":"SOxu0mWeXh96N3t9qo6a","unitId":"C0M499utiLGh647x2cnp","createdAt":{"seconds":1759057651,"nanoseconds":875000000}},{"id":"Zg4bFFfi33CItiEXOg84","courseId":"XboyC5jGWhYxh8RHYtrC","type":"definition","content":{"definition":"Peygamberimizin Mekkeli ve Medineli Müslümanlar arasında kurduğu, mallarını ve hayatlarını paylaşmaya dayalı güçlü kardeşlik sistemidir.","term":"Muâhât"},"unitId":"C0M499utiLGh647x2cnp","topicId":"SOxu0mWeXh96N3t9qo6a","createdAt":{"seconds":1759056833,"nanoseconds":496000000}},{"id":"ZwIWFhczPRwf1qf36OWG","courseId":"XboyC5jGWhYxh8RHYtrC","unitId":"C0M499utiLGh647x2cnp","type":"concept","content":{"text":"Ranuna Vadisi"},"topicId":"6FQTyaJFs3bjPjAa2OwO","createdAt":"2025-09-22T12:03:36.218Z"},{"id":"aCA3dV0gOI5kSyJYClUq","topicId":"6FQTyaJFs3bjPjAa2OwO","type":"definition","courseId":"XboyC5jGWhYxh8RHYtrC","content":{"term":"Zeyd b. Hârise","definition":"Üvey oğlu"},"unitId":"C0M499utiLGh647x2cnp","createdAt":"2025-09-22T12:03:36.218Z"},{"id":"aCIS96jO8mDano1ZBkQR","unitId":"C0M499utiLGh647x2cnp","content":{"text":"Peygamberimiz Medine'ye büyük sevinçle geldi."},"type":"sentence","topicId":"SOxu0mWeXh96N3t9qo6a","courseId":"XboyC5jGWhYxh8RHYtrC","createdAt":"2025-09-28T11:10:02.699Z"},{"id":"acxi0nV9yZVFernMSRy7","topicId":"T326A9OOHtWd4mU6bN2r","courseId":"XboyC5jGWhYxh8RHYtrC","type":"concept","content":{"text":"İbrahim"},"unitId":"C0M499utiLGh647x2cnp","createdAt":"2025-09-21T17:00:19.786Z"},{"id":"ah3L5oVJMj2n67XULv4D","topicId":"T326A9OOHtWd4mU6bN2r","unitId":"C0M499utiLGh647x2cnp","content":{"text":"Ümmü Gülsüm"},"type":"concept","courseId":"XboyC5jGWhYxh8RHYtrC","createdAt":"2025-09-21T17:00:19.786Z"},{"id":"asAfs8MMjJrAr3VGMXSy","unitId":"C0M499utiLGh647x2cnp","topicId":"T326A9OOHtWd4mU6bN2r","courseId":"XboyC5jGWhYxh8RHYtrC","type":"definition","content":{"definition":"Çocuğu","term":"Ümmü Gülsüm"},"createdAt":"2025-09-21T17:00:19.786Z"},{"id":"aviBFe0F6x349KR9zxsI","unitId":"C0M499utiLGh647x2cnp","content":{"term":"Halime","definition":"Süt annesi"},"type":"definition","topicId":"T326A9OOHtWd4mU6bN2r","courseId":"XboyC5jGWhYxh8RHYtrC","createdAt":"2025-09-21T17:00:19.786Z"},{"id":"bMKhvOIsD6BTGjjNIxgg","unitId":"C0M499utiLGh647x2cnp","content":{"text":"Akabe Biatları"},"topicId":"6FQTyaJFs3bjPjAa2OwO","type":"concept","courseId":"XboyC5jGWhYxh8RHYtrC","createdAt":"2025-09-22T12:03:36.218Z"},{"id":"cy4w6zQS7ZjsoxeEPcNZ","type":"concept","content":{"text":"Ambargo"},"topicId":"6FQTyaJFs3bjPjAa2OwO","courseId":"XboyC5jGWhYxh8RHYtrC","unitId":"C0M499utiLGh647x2cnp","createdAt":"2025-09-22T12:03:36.218Z"},{"id":"dGoBvQEzPP7T2VLXKcw5","unitId":"C0M499utiLGh647x2cnp","content":{"definition":"Kabe'de bulunan siyah taş","term":"Hacerülesved"},"topicId":"T326A9OOHtWd4mU6bN2r","courseId":"XboyC5jGWhYxh8RHYtrC","type":"definition","createdAt":"2025-09-21T17:00:19.786Z"},{"id":"dWVnAgjRzWYWlOVzmFt2","unitId":"C0M499utiLGh647x2cnp","content":{"definition":"İlk çocuğu","term":"Kasım"},"type":"definition","courseId":"XboyC5jGWhYxh8RHYtrC","topicId":"T326A9OOHtWd4mU6bN2r","createdAt":"2025-09-21T17:00:19.786Z"},{"id":"dZOzSJcXkgwTD3urP7fQ","topicId":"SOxu0mWeXh96N3t9qo6a","type":"definition","content":{"definition":"Peygamberimizin devesinin çöktüğü yere inşa edilen, günümüzde kabrinin de bulunduğu kutsal ibadet yeridir.","term":"Mescid-i Nebi"},"unitId":"C0M499utiLGh647x2cnp","courseId":"XboyC5jGWhYxh8RHYtrC","createdAt":{"seconds":1759056833,"nanoseconds":496000000}},{"id":"daUyTdrVd0F5zM8ZeIQj","type":"concept","unitId":"C0M499utiLGh647x2cnp","content":{"text":"Hanif"},"topicId":"6FQTyaJFs3bjPjAa2OwO","courseId":"XboyC5jGWhYxh8RHYtrC","createdAt":"2025-09-22T12:03:36.218Z"},{"id":"dop6Hw6W0D7RLJmWLuwF","content":{"term":"Ensar","definition":"Medine'de Peygamberimiz ve Mekke'den gelen Müslümanları ağırlayan ve onlara yardım eden yerli halka verilen isimdir."},"courseId":"XboyC5jGWhYxh8RHYtrC","unitId":"C0M499utiLGh647x2cnp","type":"definition","topicId":"SOxu0mWeXh96N3t9qo6a","createdAt":{"seconds":1759056833,"nanoseconds":496000000}},{"id":"f6v6bz4DJ0Oihcl3RIMa","content":{"term":"Hz.Ömer","definition":"2.Halife"},"topicId":"6FQTyaJFs3bjPjAa2OwO","type":"definition","unitId":"C0M499utiLGh647x2cnp","courseId":"XboyC5jGWhYxh8RHYtrC","createdAt":"2025-09-22T12:03:36.218Z"},{"id":"fE3CGtVCuDlusLR1tBzA","unitId":"C0M499utiLGh647x2cnp","type":"definition","content":{"term":"Mekke","definition":"Peygamberimizin doğduğu yer"},"courseId":"XboyC5jGWhYxh8RHYtrC","topicId":"T326A9OOHtWd4mU6bN2r","createdAt":"2025-09-21T17:00:19.786Z"},{"id":"fxGuE56sJCheBSGkWL8R","type":"concept","content":{"text":"Mus’ab b. Umeyr"},"courseId":"XboyC5jGWhYxh8RHYtrC","unitId":"C0M499utiLGh647x2cnp","topicId":"6FQTyaJFs3bjPjAa2OwO","createdAt":"2025-09-22T12:03:36.218Z"},{"id":"ggXwcFm8FsBLHBz6LZot","type":"definition","content":{"term":"Zeyneb","definition":"Çocuğu"},"topicId":"T326A9OOHtWd4mU6bN2r","unitId":"C0M499utiLGh647x2cnp","courseId":"XboyC5jGWhYxh8RHYtrC","createdAt":"2025-09-21T17:00:19.786Z"},{"id":"gptyjT80Cm7g3hhjLwa9","courseId":"XboyC5jGWhYxh8RHYtrC","topicId":"SOxu0mWeXh96N3t9qo6a","content":{"definition":"İlk müezzin","term":"Bila-i Habeşi"},"unitId":"C0M499utiLGh647x2cnp","type":"definition","createdAt":{"seconds":1759057651,"nanoseconds":875000000}},{"id":"gwzYkxeiY4ogvVyVOejA","unitId":"C0M499utiLGh647x2cnp","type":"concept","courseId":"XboyC5jGWhYxh8RHYtrC","content":{"text":"Ebu Eyyüb el-Ensârî"},"topicId":"SOxu0mWeXh96N3t9qo6a","createdAt":"2025-09-28T11:07:31.875Z"},{"id":"hCSuV3RxfJPUVCga6A4b","topicId":"6FQTyaJFs3bjPjAa2OwO","unitId":"C0M499utiLGh647x2cnp","courseId":"XboyC5jGWhYxh8RHYtrC","type":"concept","content":{"text":"Ensar"},"createdAt":"2025-09-22T12:03:36.218Z"},{"id":"hd5Ste1niAvXnkCGEB7S","courseId":"XboyC5jGWhYxh8RHYtrC","content":{"definition":"Mekke’den Medine’ye göç eden Müslümanlara denir.","term":"Muhacir"},"type":"definition","unitId":"C0M499utiLGh647x2cnp","topicId":"6FQTyaJFs3bjPjAa2OwO","createdAt":"2025-09-22T12:03:36.218Z"},{"id":"hdT8iWaZP7KmQHU4jeaH","unitId":"C0M499utiLGh647x2cnp","courseId":"XboyC5jGWhYxh8RHYtrC","topicId":"6FQTyaJFs3bjPjAa2OwO","type":"definition","content":{"term":"Dârülerkam","definition":"İslamın ilkokulu"},"createdAt":"2025-09-22T12:03:36.218Z"},{"id":"hkBVlaoaBEOBkneOeXgk","topicId":"T326A9OOHtWd4mU6bN2r","unitId":"C0M499utiLGh647x2cnp","courseId":"XboyC5jGWhYxh8RHYtrC","type":"definition","content":{"definition":"İlk eşi","term":"Hatice"},"createdAt":"2025-09-21T17:00:19.786Z"},{"id":"iHQNG0EtpTlVIanIG14G","unitId":"C0M499utiLGh647x2cnp","courseId":"XboyC5jGWhYxh8RHYtrC","content":{"definition":"Annesi","term":"Amine"},"type":"definition","topicId":"T326A9OOHtWd4mU6bN2r","createdAt":"2025-09-21T17:00:19.786Z"},{"id":"iKfatLikjgiedVsaTi4r","content":{"text":"Hudeybiye Antlaşması"},"topicId":"SOxu0mWeXh96N3t9qo6a","courseId":"XboyC5jGWhYxh8RHYtrC","unitId":"C0M499utiLGh647x2cnp","type":"concept","createdAt":"2025-09-28T11:07:31.875Z"},{"id":"ise6tKd7qANYp4E0K7nR","topicId":"6FQTyaJFs3bjPjAa2OwO","courseId":"XboyC5jGWhYxh8RHYtrC","unitId":"C0M499utiLGh647x2cnp","content":{"definition":"İlk Cuma namazının kılındığı yer","term":"Ranuna Vadisi"},"type":"definition","createdAt":"2025-09-22T12:03:36.218Z"},{"id":"iuLDpMV5dCL39K9AylYS","courseId":"XboyC5jGWhYxh8RHYtrC","unitId":"C0M499utiLGh647x2cnp","type":"concept","topicId":"T326A9OOHtWd4mU6bN2r","content":{"text":"Zeyneb"},"createdAt":"2025-09-21T17:00:19.786Z"},{"id":"jphbAdC5kybn49tSFBhJ","content":{"text":"Taif"},"courseId":"XboyC5jGWhYxh8RHYtrC","type":"concept","topicId":"6FQTyaJFs3bjPjAa2OwO","unitId":"C0M499utiLGh647x2cnp","createdAt":"2025-09-22T12:03:36.218Z"},{"id":"jwvwY4z1dD7w0Mt3vFLO","type":"definition","unitId":"C0M499utiLGh647x2cnp","content":{"definition":"İlk öğretmen","term":"Mus’ab b. Umeyr"},"topicId":"6FQTyaJFs3bjPjAa2OwO","courseId":"XboyC5jGWhYxh8RHYtrC","createdAt":"2025-09-22T12:03:36.218Z"},{"id":"kYb4Nua6shwWlVr6W0tk","type":"definition","topicId":"SOxu0mWeXh96N3t9qo6a","content":{"term":"Medine Sözleşmesi","definition":"Peygamberimizin şehirdeki tüm inanç gruplarıyla sosyal dayanışmayı ve barışı temin etmek için imzaladığı ilk anayasal belgedir."},"unitId":"C0M499utiLGh647x2cnp","courseId":"XboyC5jGWhYxh8RHYtrC","createdAt":{"seconds":1759056833,"nanoseconds":496000000}},{"id":"khIRY6KXxPWBMEBrD9kf","topicId":"6FQTyaJFs3bjPjAa2OwO","content":{"definition":"Allah Resulü’nün (sav) göklere yükseltilmesi","term":"Miraç"},"type":"definition","unitId":"C0M499utiLGh647x2cnp","courseId":"XboyC5jGWhYxh8RHYtrC","createdAt":"2025-09-22T12:03:36.218Z"},{"id":"lNUULpTm28fHLrTIEo3M","unitId":"C0M499utiLGh647x2cnp","courseId":"XboyC5jGWhYxh8RHYtrC","content":{"term":"Rukiye","definition":"Çocuğu"},"topicId":"T326A9OOHtWd4mU6bN2r","type":"definition","createdAt":"2025-09-21T17:00:19.786Z"},{"id":"ln82z4VnmpRGt1oreeDB","unitId":"C0M499utiLGh647x2cnp","content":{"term":"Ebülkasım","definition":"Peygamberimizin künyesi"},"topicId":"T326A9OOHtWd4mU6bN2r","courseId":"XboyC5jGWhYxh8RHYtrC","type":"definition","createdAt":"2025-09-21T17:00:19.786Z"},{"id":"mXd0dD5SxFhAd8CrFf47","courseId":"XboyC5jGWhYxh8RHYtrC","type":"definition","topicId":"6FQTyaJFs3bjPjAa2OwO","content":{"definition":"Hz. İbrahim'in getirdiği dine mensup, Allah'ın (c.c.) birliğine inanan ve şirkten uzak olan kimselerdir.","term":"Hanif"},"unitId":"C0M499utiLGh647x2cnp","createdAt":"2025-09-22T12:03:36.218Z"},{"id":"mxiSrYfGbwx7Kd6bf0xU","type":"definition","unitId":"C0M499utiLGh647x2cnp","content":{"definition":"Peygamberimizin amcası","term":"Hz.Hamza"},"topicId":"6FQTyaJFs3bjPjAa2OwO","courseId":"XboyC5jGWhYxh8RHYtrC","createdAt":"2025-09-22T12:03:36.218Z"},{"id":"nAuWjusOwPjpXPMfsA4a","topicId":"SOxu0mWeXh96N3t9qo6a","unitId":"C0M499utiLGh647x2cnp","type":"sentence","content":{"text":"Medine Sözleşmesi şehirde birlik sağladı."},"courseId":"XboyC5jGWhYxh8RHYtrC","createdAt":"2025-09-28T11:10:02.699Z"},{"id":"nDMAbOvs5o5jOhXPMFat","content":{"text":"Bedir, Uhud ve Hendek savaşları yapıldı."},"unitId":"C0M499utiLGh647x2cnp","type":"sentence","topicId":"SOxu0mWeXh96N3t9qo6a","courseId":"XboyC5jGWhYxh8RHYtrC","createdAt":"2025-09-28T11:10:02.699Z"},{"id":"nms7FaP4mCvlSW7HSQwc","type":"sentence","topicId":"SOxu0mWeXh96N3t9qo6a","content":{"text":"Ezan uygulaması başlatıldı. İlk eznı Bilal-i Habeşi okudu."},"unitId":"C0M499utiLGh647x2cnp","courseId":"XboyC5jGWhYxh8RHYtrC","createdAt":"2025-09-28T11:10:02.699Z"},{"id":"oVlaoAUEDs42UKmKfItu","content":{"text":"Ebülkasım"},"type":"concept","unitId":"C0M499utiLGh647x2cnp","topicId":"T326A9OOHtWd4mU6bN2r","courseId":"XboyC5jGWhYxh8RHYtrC","createdAt":"2025-09-21T17:00:19.786Z"},{"id":"oomIH62gN8A4Epbpb0rB","topicId":"T326A9OOHtWd4mU6bN2r","content":{"text":"Peygamberimiz 4 yaşına kadar sütannesi Halime, 6 yaşına kadar annesi Amine, 8 yaşına kadar dedesi Abdülmüttalib'in yanında kaldı."},"courseId":"XboyC5jGWhYxh8RHYtrC","unitId":"C0M499utiLGh647x2cnp","type":"sentence","createdAt":"2025-09-21T17:00:19.786Z"},{"id":"pNAEM1F8yEIs59qj7w5a","content":{"definition":"Hz. Peygamber'in bizzat komuta ederek katıldığı askeri seferlere verilen isimdir.","term":"Gazve"},"unitId":"C0M499utiLGh647x2cnp","courseId":"XboyC5jGWhYxh8RHYtrC","topicId":"SOxu0mWeXh96N3t9qo6a","type":"definition","createdAt":{"seconds":1759056833,"nanoseconds":496000000}},{"id":"qAWVacNijFHrthpSY2To","content":{"definition":"İkinci savaş","term":"Uhud Savaşı"},"topicId":"SOxu0mWeXh96N3t9qo6a","courseId":"XboyC5jGWhYxh8RHYtrC","type":"definition","unitId":"C0M499utiLGh647x2cnp","createdAt":{"seconds":1759057651,"nanoseconds":875000000}},{"id":"qDNzpwiZYdf422CToeox","unitId":"C0M499utiLGh647x2cnp","topicId":"6FQTyaJFs3bjPjAa2OwO","type":"concept","courseId":"XboyC5jGWhYxh8RHYtrC","content":{"text":"Hz.Ömer"},"createdAt":"2025-09-22T12:03:36.218Z"},{"id":"qhqS01u3osF0njrRAXoa","topicId":"T326A9OOHtWd4mU6bN2r","type":"concept","courseId":"XboyC5jGWhYxh8RHYtrC","content":{"text":"Kâbe Hakemliği"},"unitId":"C0M499utiLGh647x2cnp","createdAt":"2025-09-21T17:00:19.786Z"},{"id":"rPOqhWQYKZjKYpR9XaFP","topicId":"SOxu0mWeXh96N3t9qo6a","courseId":"XboyC5jGWhYxh8RHYtrC","unitId":"C0M499utiLGh647x2cnp","type":"definition","content":{"term":"Bedir Savaşı","definition":"İlk savaş"},"createdAt":{"seconds":1759057651,"nanoseconds":875000000}},{"id":"rrcgnwFuixHfEJMaLSbv","content":{"text":"Hz.Hamza"},"unitId":"C0M499utiLGh647x2cnp","type":"concept","topicId":"6FQTyaJFs3bjPjAa2OwO","courseId":"XboyC5jGWhYxh8RHYtrC","createdAt":"2025-09-22T12:03:36.218Z"},{"id":"ry6C61TWgUkyBCBYThtQ","type":"definition","courseId":"XboyC5jGWhYxh8RHYtrC","topicId":"SOxu0mWeXh96N3t9qo6a","content":{"definition":"Tertemiz gül bahçesi","term":"Ravza-i Mutahhara"},"unitId":"C0M499utiLGh647x2cnp","createdAt":{"seconds":1759057651,"nanoseconds":875000000}},{"id":"rzuzjIERavOp8frtIqI3","topicId":"6FQTyaJFs3bjPjAa2OwO","content":{"definition":"Evini İslam'a açan sahabi","term":"Erkam b. Ebi’l-Erkam"},"type":"definition","unitId":"C0M499utiLGh647x2cnp","courseId":"XboyC5jGWhYxh8RHYtrC","createdAt":"2025-09-22T12:03:36.218Z"},{"id":"sHuq223STPtCQFwLGdvI","type":"definition","topicId":"T326A9OOHtWd4mU6bN2r","courseId":"XboyC5jGWhYxh8RHYtrC","unitId":"C0M499utiLGh647x2cnp","content":{"definition":"Babası","term":"Abdullah"},"createdAt":"2025-09-21T17:00:19.786Z"},{"id":"sRTxdMVrxg6p9rp4ZNbh","type":"definition","content":{"term":"Veda Hutbesi","definition":"Peygamberimizin son haccında Arafat'ta verdiği ve insan hakları prensiplerini içeren tarihi konuşmasıdır."},"courseId":"XboyC5jGWhYxh8RHYtrC","topicId":"SOxu0mWeXh96N3t9qo6a","unitId":"C0M499utiLGh647x2cnp","createdAt":{"seconds":1759056833,"nanoseconds":496000000}},{"id":"trlZTDoKbqgxPAFIxBz4","content":{"definition":"Peygamberimizin hicretinden sonra Yesrib şehrine verilen ve \"aydınlanmış şehir\" anlamına gelen isimdir.","term":"Medine"},"unitId":"C0M499utiLGh647x2cnp","type":"definition","courseId":"XboyC5jGWhYxh8RHYtrC","topicId":"SOxu0mWeXh96N3t9qo6a","createdAt":{"seconds":1759056833,"nanoseconds":496000000}},{"id":"uBHMdN6wdwmD7wM1EW3N","unitId":"C0M499utiLGh647x2cnp","content":{"term":"Hilfülfudul","definition":"Erdemliler Birliği"},"topicId":"T326A9OOHtWd4mU6bN2r","type":"definition","courseId":"XboyC5jGWhYxh8RHYtrC","createdAt":"2025-09-21T17:00:19.786Z"},{"id":"v7Bz2qmTHfDUXOY2mZmO","topicId":"T326A9OOHtWd4mU6bN2r","type":"concept","courseId":"XboyC5jGWhYxh8RHYtrC","content":{"text":"Ebu Talib"},"unitId":"C0M499utiLGh647x2cnp","createdAt":"2025-09-21T17:00:19.786Z"},{"id":"vbSq1gSh8bVCkMY6n873","unitId":"C0M499utiLGh647x2cnp","topicId":"6FQTyaJFs3bjPjAa2OwO","type":"sentence","content":{"text":"Ey İnananlar! Sabır ve namazla Allah’tan yardım dileyin. Allah, muhakkak ki sabredenlerle beraberdir."},"courseId":"XboyC5jGWhYxh8RHYtrC","createdAt":"2025-09-22T12:03:36.218Z"},{"id":"vmxn0WCbSKnXm24RmLO6","type":"definition","courseId":"XboyC5jGWhYxh8RHYtrC","topicId":"6FQTyaJFs3bjPjAa2OwO","unitId":"C0M499utiLGh647x2cnp","content":{"definition":"Alak Suresi 1-5 ayetler","term":"İlk vahiy"},"createdAt":"2025-09-22T12:03:36.218Z"},{"id":"vsjZYmNK1oBJZV4oeAkn","unitId":"C0M499utiLGh647x2cnp","type":"concept","courseId":"XboyC5jGWhYxh8RHYtrC","topicId":"6FQTyaJFs3bjPjAa2OwO","content":{"text":"Tevhit"},"createdAt":"2025-09-22T12:03:36.218Z"},{"id":"wKFSjL5WjsSrGnvWfgs1","content":{"term":"Fil Vakası","definition":"Peygamberimizin doğduğu yıl meydana gelen olay"},"topicId":"T326A9OOHtWd4mU6bN2r","unitId":"C0M499utiLGh647x2cnp","type":"definition","courseId":"XboyC5jGWhYxh8RHYtrC","createdAt":"2025-09-21T17:00:19.786Z"},{"id":"wSryvigm9CLglywiXjaw","topicId":"SOxu0mWeXh96N3t9qo6a","courseId":"XboyC5jGWhYxh8RHYtrC","unitId":"C0M499utiLGh647x2cnp","type":"concept","content":{"text":"Bedir Savaşı"},"createdAt":"2025-09-28T11:07:31.875Z"},{"id":"wYjALgdhloUaODy7HSIA","courseId":"XboyC5jGWhYxh8RHYtrC","content":{"text":"Hendek Savaşı"},"unitId":"C0M499utiLGh647x2cnp","type":"concept","topicId":"SOxu0mWeXh96N3t9qo6a","createdAt":"2025-09-28T11:07:31.875Z"},{"id":"yJqlY4GvgRdtlDPWOElv","unitId":"C0M499utiLGh647x2cnp","content":{"text":"İlk vahiy"},"type":"concept","courseId":"XboyC5jGWhYxh8RHYtrC","topicId":"6FQTyaJFs3bjPjAa2OwO","createdAt":"2025-09-22T12:03:36.218Z"},{"id":"zF3lP6oRzG1b2xyavXZ3","type":"definition","topicId":"6FQTyaJFs3bjPjAa2OwO","unitId":"C0M499utiLGh647x2cnp","content":{"term":"Tefekkür","definition":"Derin düşünme, fikir yürütme, kavramaya çalışma ve kafa yormadır."},"courseId":"XboyC5jGWhYxh8RHYtrC","createdAt":"2025-09-22T12:03:36.218Z"},{"id":"ziV4kkWJxbgMGGaZFyRQ","content":{"term":"Cahiliye","definition":"Arapların İslam’dan önceki inanç, tutum ve davranışlarını İslam’ın kabulünden sonraki dönemden ayırt etmek için kullanılan bir kavramdır."},"unitId":"C0M499utiLGh647x2cnp","topicId":"T326A9OOHtWd4mU6bN2r","courseId":"XboyC5jGWhYxh8RHYtrC","type":"definition","createdAt":"2025-09-21T17:00:19.786Z"},{"id":"zn7sLnPOYnNNujP39SJq","topicId":"6FQTyaJFs3bjPjAa2OwO","type":"concept","unitId":"C0M499utiLGh647x2cnp","content":{"text":"İsra"},"courseId":"XboyC5jGWhYxh8RHYtrC","createdAt":"2025-09-22T12:03:36.218Z"},{"id":"zq3yIey5nOWQHPaIi17v","type":"definition","courseId":"XboyC5jGWhYxh8RHYtrC","content":{"term":"Ebu Talib","definition":"Amcası"},"topicId":"T326A9OOHtWd4mU6bN2r","unitId":"C0M499utiLGh647x2cnp","createdAt":"2025-09-21T17:00:19.786Z"}]