[
  {
    "id": "03lmGqXTa8ejb174SiHt",
    "title": "4. Ünite: Toplumsal Hayatta Peygamberimiz",
    "createdAt": "2025-09-15T16:44:23.246Z"
  },
  {
    "id": "0M2x5SEKuVmzS3qhwvPk",
    "title": "1. Ünite: Gençlik Yıllarında Peygamberimiz",
    "createdAt": "2025-09-15T16:44:23.246Z"
  },
  {
    "id": "ARSRniTfx324ZswltLyy",
    "title": "3. Ünite: Rehberim Peygamberim",
    "createdAt": "2025-09-15T16:44:23.246Z"
  },
  {
    "id": "t9HH1JF2D3UIsCnmUkWa",
    "title": "2. Ünite: Peygamberimizin Çevresindeki Gençler",
    "createdAt": "2025-09-15T16:44:23.246Z",
    "sourceText": "Üniteye Başlarken\nHz. Peygamber’in çevresindeki genç sahibiler, ona her zaman derin bir saygı duymuşlardır. Onunla konuşurken hem ses tonlarının hem de hitap şekillerinin uygun olmasına büyük bir özen göstermişlerdir. Sevgili Peygamberimize olan saygılarını yalnızca sözleriyle değil davranışlarıyla da ifade etmişlerdir. Bu durumu, sahabilerden Üsame bin Şerîk (ra) şöyle anlatmıştır: “Resulullah konuştuğunda sahabileri, başlarının üzerinde kuş varmış gibi sessiz ve dikkatli bir şekilde onu dinlerlerdi.” Genç sahibiler, Hz. Peygamber’in söz ve davranışlarına büyük değer vermiş, onun nasihatlerini dikkatle dinleyip hayatlarına uygulamış ve onun gibi yaşamaya gayret etmişlerdir.\n(Ahmed bin Hanbel, el-Müsned, 30/394)\nSahabilerin Peygamber Efendimiz’e gösterdiği saygı ile toplumumuzdaki gençlerin büyüklere gösterdiği saygı arasındaki benzerlikler nelerdir? Örneklerle açıklayınız.\n492. Ünite\n2.1. Peygamberimizin Gençlerle İletişimi\nKonuya Başlarken\nHz. Peygamber, dedesi ve amcasının yanında sevgi ve saygı içinde büyütülmüş-\ntür. Amcası ona her zaman güven duymuş ve onun erken yaşlarda ticaret hayatına\natılmasına yardımcı olmuştur. Hz. Muhammed (sav), kısa zamanda çalışkanlığı,\ndürüstlüğü ile tanınan ve insanlara güven veren bir genç hâline gelmiştir. Gençlik\nyıllarında da çevresinde yaşananlara karşı olgun bir tavır sergilemiştir. Genç yaşta\nsahip olduğu ahlaki değerler onun sadece büyüklerin değil gençlerin de sevgi, say-\ngı ve güvenini kazanmasını sağlamıştır.\n1. Hz. Peygamber’in gençlik yıllarındaki tecrübeleri onun gençlerle ilgili\nduygu ve tutumlarını nasıl etkilemiş olabilir? Düşüncelerinizi arka-\ndaşlarınızla paylaşınız.\n2. Hz. Peygamber gençlerle iletişiminde onlara nasıl değer vermiş olabi-\nlir? Düşüncelerinizi açıklayınız.\nYüce Allah, kullarına olan merhametinden dolayı insanlara yol gös-\ntermeleri için birçok peygamber göndermiştir. Hz. Muhammed (sav)\npeygamberlerin sonuncusudur. İnsanlığa bir peygamber gönderilmemiş\nolsaydı insanlar kendilerini doğru yola iletecek bir rehberden mahrum ka-\nlırdı. Bu sebeple Allah (cc) “Ve seni ancak alemlere rahmet ola-\nrak gönderdik.”1 (Görsel 2.1) buyurmuştur.\nGörsel 2.1\nHz. Muhammed (sav)\nbütün dünyaya rahmet\nolarak gönderilmiştir.\nHz. Peygamber’in\ngençlerle iletişimi\nhakkında daha fazla\nbilgiye ulaşmak için\nkarekodu okutunuz.\nRahmet, kelime manası olarak merhamet etmek, sevmek ve şefkat gös-\ntermek anlamlarına gelir.2 İnsanlığa Allah’ın (cc) bir rahmeti olarak gön-\nderilen Hz. Muhammed (sav), insanlara her zaman şefkat ve merhamet\ntemelli bir yaklaşım sergilemiştir. Hz. Muhammed (sav), kendisine kar-\nşı savaşan insanlara bile merhametle yaklaşmıştır. Uhud Savaşı’nda\nMüslümanlar büyük kayıplar vermiştir. Hatta müşrikler, Hz. Peygamber’in\nyanına çok yaklaşmışlardır. Sahabiler, canları pahasına ona siper\nolmuş fakat Hz. Peygamber’in yüzünden yaralanmasına engel ola-\nmamışlardır. Böyle bir durumda bile Sevgili Peygamberimiz, kendini\ndüşünmek yerine, ona düşmanlık yapanları affetmiş ve Allah’ın (cc)\nonlara gazap etmesinden korkarak şöyle demiştir: “Allah’ım, kavmimi\naffet, çünkü onlar bilmiyorlar.”3\n50Peygamberimizin Çevresindeki Gençler\nSevgili Peygamberimiz, herkesi kuşatan bir şefkat ve merhamete sa-\nhipti. Hayatı yeni öğrenmeye başlayan çocuklar ve gençler söz konusu\nolduğunda ise bu konuda daha hassas davranmaya özen göstermiştir.\nKüçüklere şefkat ve merhametle yaklaşılması, onun önemli bir sünneti\nolarak nesiller boyu devam etmiştir.\n1. Etkinlik\nAdı\nHz. Peygamber’in Gençlere Verdiği Değer\nAmaç Hz. Peygamber’in gençlerle iletişimde onlara verdiği değere ilişkin bilgileri araştırabilme\nYönerge: Kutularda, bazı genç sahabilerin Sevgili Peygamberimiz hakkındaki görüşleri\nverilmiştir. Bu cümlelerden yola çıkarak Hz. Peygamber’in gençlerle iletişim kurarken nelere\ndikkat ettiğini boşluğa yazınız.\nA\nEnes bin Malik (ra) şöyle demiştir:\n“Resulullah, kötü sözler söyleyen birisi\ndeğildi...”4\nB\nCerir bin Abdullah (ra) şöyle\ndemiştir: “Müslüman olduğum günden\nberi Resulullah beni hiç kapıdan\nçevirmedi. Beni her gördüğünde\nmutlaka gülümserdi.”5\n1 Saat\nC\nD\nResulullah, Hz. Aişe’ye şöyle\nbuyurmuştur: “... Allah beni sıkıntı verip\nzorlaştırıcı olarak göndermedi. Beni\nancak kolaylaştırıcı bir\nöğretmen olarak gönderdi.”6\nAbdullah bin Mesud (ra) şöyle\ndemiştir: “Peygamber (sav) bizleri\nusandırmamak amacıyla vaaz\niçin belli günler kollardı.”7\nDeğerlendirme: Karekoddaki öz değerlendirme formunu doldurunuz.\n512. Ünite\nOkuma Metni\nMetinden hareketle soruları cevaplayınız.\nEbu Mahzure’nin Hikâyesi\nHz. Muhammed (sav), Mekke’yi fethettikten sonra müşrikler büyük bir yenilgi yaşadı. Bir-\nçok müşrik Müslümanlığı seçerken bazıları ise Hz. Peygamber’e karşı kin besliyordu. Ebu\nMahzure de Mekke’nin fethinden dolayı Sevgili Peygamberimize karşı kin tutuyordu. Ebu\nMahzure, bir gün kendisi gibi müşrik olan arkadaşları ile Ci’râne bölgesinde oturuyordu.\nAynı gün Hz. Peygamber ve ordusu, Taif kuşatmasından dönmekteydi ve Cir’âne bölgesin-\nde mola vermeye karar verdiler. Müslümanlar, ezan okumaya başlayınca Ebu Mahzure ve\narkadaşları bir yere gizlenip alaylı bir şekilde ezanı taklit etmeye başladılar. Sahabiler, genç-\nlerin bu hareketine kızarken Sevgili Peygamberimiz onlardan birinin sesinin çok güzel ol-\nduğunu fark etti ve gençleri yanına çağırttı. Gençler kendilerine büyük bir ceza verileceğini\ndüşünürken Hz. Peygamber, içlerinden sesi en güzel olan Ebu Mahzure’ye yöneldi. Ona\nezanı öğretti ve okumasını istedi. Ebu Mahzure ezanı okumak istemiyordu ama bir yandan\nda artık buna mecbur kalmıştı. Ebu Mahzure ezanı okuduktan sonra Sevgili Peygamberimiz,\nona bir miktar gümüş para verdi. Daha sonra şefkatle elini Ebu Mahzure’nin başına koya-\nrak onun alnını okşadı ve ona dua etti. Bu durum Ebu Mahzure’nin kalbini yumuşattı. Ebu\nMahzure orada Müslüman oldu. Hz. Peygamber’den kendisini Mekke’ye müezzin olarak\ngörevlendirmesini istedi. Sevgili Peygamberimiz, onun bu isteğini kabul etti. Ebu Mahzure,\nömrünün sonuna kadar Mekke’de müezzinlik yaptı. Rivayete göre Ebu Mahzure, bu olaydan\nçok etkilendi. Hatta Sevgili Peygamberimiz okşadı diye uzun süre başının önündeki saçları\ndahi kestirmek istemedi.\n(bk. Sarıcık, “Ebu Mahzure”, 10/179)\n1. Ebu Mahzure’nin yerinde siz olsaydınız Hz. Peygamber’in anlayışlı tavrı karşısında ne\ndüşünürdünüz?\n2. Peygamber Efendimiz, Ebu Mahzure’yi hangi sebeplerden dolayı müezzin olarak gö-\nrevlendirmiştir?\nSevgili Peygamberimiz ile yaşayan gençler, onun merhamet ve şef-\nkatinden o kadar eminlerdi ki her türlü duygu ve düşüncelerini onunla\npaylaşmaktan çekinmemişlerdir. Peygamber Efendimiz, karşısındaki\ngenç hatalı dahi olsa ona karşı yumuşak bir dil kullanmaya özen göster-\nmiştir. Küçük yaşından itibaren onun gözetiminde yetişmiş olan Enes\nbin Malik (ra), bu durumu şu şekilde ifade etmiştir: “On sene boyunca\nResullulah’ın yanında bulundum. Yüce Allah’a yemin ederim ki bir kez\nolsun bana ‘Öf!’ bile demedi. Herhangi bir şeyden dolayı bana ‘Niçin\nböyle yaptın?’ demediği gibi ‘Şöyle yapsaydın ya!’ da demedi.”8\n52Peygamberimizin Çevresindeki Gençler\nHz. Peygamber, gençlere değer vermiş ve onların duygularını anla-\nmaya çalışmıştır. Bir grup Müslüman genç, İslam’ı öğrenmek amacıyla\nMedine’ye gelmişti. Bir süre Hz. Peygamber’in yanında kalan bu genç-\nler, memleketlerinden uzak kaldıkları için ailelerini özlemişlerdi. Bu\ndurumu fark eden Hz. Peygamber, gençlerle aileleri hakkında sohbet\netmiştir. Ardından onlara ailelerinin yanlarına dönmelerini ve burada\nöğrendiklerini kendi toplumlarına öğretmelerini önermiştir.9\n2. Etkinlik\nAdı\nÖğrenme Günlüğüm\nAmaç Hz. Peygamber’in gençlerle iletişimde onlara verdiği değeri sentezleyebilme\nYönerge: Uygulama basamaklarını takip ederek etkinliği tamamlayınız.\n1. Beşer kişilik gruplara ayrılınız.\n2. Hz. Peygamber’in gençlerle iletişimi ve onlara verdiği değer ile ilgili örnek olay araştır-\nması yapınız.\n3. Grup arkadaşlarınızla belirlediğiniz bir örnek olayı, gençlerin dilinden anlatılacak şekilde\ndrama etkinliğine dönüştürerek arkadaşlarınıza sergileyiniz.\n4. Drama sonunda, verilen öğrenme günlüğünü bireysel olarak doldurunuz.\nHz. Peygamber’in gençlerle iletişimine dair önceden bildiklerim\n1 Hafta\nHz. Muhammed’in (sav) gençlerle iletişimine dair yeni öğrendiklerim\nDrama etkinliği sonucunda Hz. Peygamber’in gençlerle iletişimine karşı hissettiklerim\nDeğerlendirme: Karekoddaki grup değerlendirme formunu doldurunuz.\n532. Ünite\nHz. Peygamber, çevresindeki gençleri tanımaya özen göstermiştir.\nGenç sahabilerin yeteneklerini keşfeden Hz. Peygamber, onları doğru\nbir şekilde yönlendirmiştir. Sevgili Peygamberimiz, gençlerin kendi ye-\nteneklerini keşfetmelerine de yardımcı olmuştur. Onların güçlü yönlerini\nön plana çıkararak gençleri takdir etmiştir. Bazı genç sahabileri ilmî açı-\ndan teşvik ederken bazılarını askerî alanda görevlendirmiş, yönetim\nkabiliyeti olanları ise erken yaşlardan itibaren yöneticilik görevlerine\natamıştır.\nİslam’ın insanlar tarafından hızlı bir şekilde benimsenmesinde\nHz. Peygamber’in insanlarla kurduğu doğru iletişimin önemli bir etkisi ol-\nmuştur. Yüce Allah şöyle buyurmuştur: “Sen onlara sırf Allah’ın lüt-\nfettiği merhamet sayesinde yumuşak davrandın. Eğer kaba, katı\nkalpli olsaydın, hiç şüphesiz etrafından dağılır giderlerdi... ”10\nistişare\nGörüş alışverişinde\nbulunma, fikir alma,\ndanışma (Serinsu\nvd., “istişare”, 184)\nGörsel 2.2\nHz. Peygamber,\nönemli kararlar alırken\nistişare etmeyi\nöğütlemiştir.\nHz. Peygamber’in gençlerle kurduğu iletişimde önemli unsurlardan biri\nde onlarla istişare etmesiydi. O, çevresindeki insanların akıl ve tecrü-\nbelerine değer vererek doğru ve etkili kararlar alabilmek için istişareye\nbüyük önem vermiştir. Bu durum, Ebu Hüreyre’nin (ra) şu sözünden\nde anlaşılmaktadır: “Ashabıyla, Resulullah’tan daha fazla istişare eden\nhiç kimseyi görmedim.”11\nİstişare, Kur'an-ı Kerim'de emredilen ve bu nedenle de Müslümanla-\nrın önem verdiği bir uygulamadır. “... İşler hakkında onlara danış,\nbir karar verince de Allah’a güven...”12\nayeti gereğince Hz. Peygamber,\nönemli kararları almadan önce her zaman çevresine danışmıştır (Görsel\n2.2). Örneğin Hudeybiye Antlaşması’ndan sonra antlaşma şartlarının\nağırlığı karşısında sahabiler nasıl hareket edecekleri konusunda ka-\nrarsız kalmışlardır. Hz. Peygamber, doğru ve etkili bir karar alabilmek\niçin eşi Ümmü Seleme (ra) ile istişare etmiş ve onun tavsiyelerine göre\nhareket etmiştir.13\nBenzer şekilde, Bedir Savaşı’nda ordunun konuşlana-\ncağı en uygun yer konusunda sahabileriyle istişare etmiştir. Sahabeden\nHubab bin Münzir’in (ra) önerisinin stratejik açıdan en doğru karar olma-\nsından dolayı ordunun yerini değiştirmiştir.14\n54Peygamberimizin Çevresindeki Gençler\nSevgili Peygamberimiz, gençleri sorumluluk alma ve bu sorumluluğu\nyerine getirme konusunda yetiştirmiştir. Bunun en güzel örneklerinden\nbiri Muaz bin Cebel’dir (ra). O, Asrısaadet’te Kur’an-ı Kerim’i ezbere\nbilen sayılı sahabiden biriydi. Hz. Peygamber, Muaz bin Cebel’i (ra)\nKur’an-ı Kerim’i insanlara öğretmesi için teşvik etmiştir. Resulullah, onun\nilmî yönünü her daim takdir etmiş ve âlimlere öncülük edeceğini ifade\netmiştir.15\nHz. Peygamber, yetkinliğine güvendiği Muaz bin Cebel’i (ra)\nYemen’e kadı olarak göndermiştir. Muaz bin Cebel’e (ra) büyük bir so-\nrumluluk veren Hz. Peygamber, onu görev yerine göndermeden önce\nbu büyük sorumluluğa karşı hazırlamaya çalışmıştır.16\nGenç sahabiler için sorumluluklarını yerine getirmek her zaman kolay\nolmamıştır. Sorumluluklarını yerine getirme konusunda hata yaptıkları\nzamanlar olmuştur (Görsel 2.3). Kab bin Malik (ra), Peygamber Efendimiz’i\nçok sever ve her zaman onun yanında bulunurdu. Ancak zor bir sefer\nolan Tebük Seferi’ne gitme konusunda geç kaldı ve sefere çıkamadı.\nSevgili Peygamberimiz seferden döndüğü zaman Kab bin Malik (ra)\nona geldi ve durumunu dürüst bir şekilde izah etti. Hatasına pişman\noldu ve tövbe etti. Tövbesi kabul edilince de bütün malını Allah (cc) yo-\nlunda feda etmek istedi. Sevgili Peygamberimiz ise ona tüm malını\ndeğil sadece bir kısmını Allah (cc) yolunda sadaka olarak dağıtmasını\nemretti.17\nSevgili Peygamberimiz sahabilere hatalarından ders çıkarmayı ve bu\nhataların nasıl telafi edileceğini öğretmiştir. Örneğin Muaz bin Cebel’e\n(ra) şu tavsiyelerde bulunmuştur: “Nerede olursan ol, Allah’a karşı gel-\nmekten sakın ve hassas bir kulluk bilinciyle hareket et! Yaptığın kötü-\nlüğün ardından bir iyilik yap ki onu yok etsin ve temizlesin. İnsanlara\nkarşı da güzel ahlakla davran!”18\nGörsel 2.3\nHatalı davranışlarımızı\ntelafi etmenin\nyollarından biri de\nhediyeleşmektir.\nAsrısaadet’teki genç-\nlerle ilgili e-içeriğe\nulaşmak için karekodu\nokutunuz.\n552. Ünite\nOkuma Metni\nMetinden hareketle soruları cevaplayınız.\nHatanın Telafisi\nBir gün Ebu Zer (ra) ve Bilal Habeşi (ra) arasında bir tartışma oldu. Ebu Zer (ra), kızgınlık\nile Bilal Habeşi’yi (ra) ten renginin farklı olmasından dolayı aşağıladı. Bu duruma çok üzülen\nBilal Habeşi, olanları Hz. Peygamber’e anlattı. Bunun üzerine Sevgili Peygamberimiz, Ebu\nZer’i (ra) gördüğü bir yerde onu bu davranışından dolayı uyardı ve “Ebu Zer! Onu annesin-\nden dolayı mı ayıplıyorsun? Demek ki sen, kendisinde hâlâ cahiliyeden izler bulunan bir kim-\nsesin.” dedi. Bu uyarı üzerine Ebu Zer (ra), yaptığına çok pişman oldu. Hatasını düzeltmek\nistedi ve Bilal Habeşi’nin (ra) yanına giderek ondan özür diledi. Bu olaydan sonra Ebu Zer (ra),\ninsanları asla aşağılamadı.\n(Müslim, “Eyman”, 38; Buhari, “İman”, 22)\n1. Anlatılan olaya göre Ebu Zer (ra), Bilal Habeşi’den (ra) niçin özür dilemiştir?\n2. Günlük hayatta hatalarınızı telafi etmek için hangi davranışlarda bulunuyorsunuz? Bu\ndurumla ilgili yaşadığınız bir olayı arkadaşlarınızla paylaşınız.\nGençleri cesaretlendirdi.\nGençlere değer verdi.\nHz. Peygamber\ngençlerle nasıl\niletişim kurdu?\nGençlere karşı her zaman\nmerhametli oldu.\nGençlerin, toplumun yanlış yönlerini\nsorgulamalarını sağladı.\nGençlere güvendi ve sorumluluklar\nverdi.\nBilgi Görseli 2.1: Hz. Peygamber’in gençlerle kurduğu iletişimin özellikleri\n56Peygamberimizin Çevresindeki Gençler\nHikaye Köşesi\nMetinden hareketle soruyu cevaplayınız.\nZehra’nın Sorumluluk Yolculuğu\nZehra; Enes bin Malik (ra), Hz. Aişe, Hz. Fatıma, Muaz bin Cebel (ra) gibi genç sahabilerin\nhayatlarını okumayı çok severdi. Sahabilerin özellikle küçük yaşlardan itibaren büyük so-\nrumluluklar üstlenmiş ve bu sorumlulukları başarıyla yerine getirmiş olmaları onu derinden\netkilerdi. Her zaman “Bir gün ben de onların yaptığı gibi büyük işler başarabilir miyim?” diye\ndüşünürdü. İçindeki bu isteği ve azmi desteklemek için öğretmeninden yardım istedi.\nÖğretmeni ise Zehra’ya “Öncelikle seni genç sahabileri örnek alma isteğinden dolayı tebrik\nederim. Onlar, Allah'ın (cc) dinini yaymak için çok büyük sorumluluklar aldılar. Peygamber\nEfendimiz, çevresindeki genç sahabileri büyük görevlerle değil onlara önce küçük görevler\nvererek eğitmiştir. Gençlere öncelikle inanç ve ibadet noktasında Allah’a (cc) karşı sorumlu-\nluklarını öğretmiş ardından onlara ailelerine, çevrelerine ve doğaya karşı olan görevlerinden\nbahsetmiştir. Böylece Sevgili Peygamberimiz, gençlere sorumluluk duygusunu aşılamıştır.\nKüçük sorumlulukları doğru şekilde yerine getirenler, zamanla daha büyük sorumlulukları taşı-\nmaya hazır hâle gelirler.” dedi.\nÖğretmeninin bu sözleri Zehra’nın zihninde bir fikir uyandırdı. Bir yandan genç sahabileri\nörnek almak istiyordu ancak kendi hayatına dönüp baktığında bazı sorumluluklarını yerine\ngetirirken yeterince dikkatli olmadığını fark etti. Bu düşüncelerle eve dönerken öğretmeninin\nsöylediklerini hatırladı ve kendi hayatında bir değişiklik yapmaya karar verdi.\nİlk olarak namazlarını daha dikkatli kılmaya başladı. Namazın, Allah’a (cc) karşı önemli bir\nsorumluluk olduğunu düşündükçe her namazını titizlikle kılmaya özen gösterdi. Ardından ki-\nşisel temizlik ve günlük ödevleri konusunda da daha dikkatli olmaya karar verdi. Annesinin\nyükünü hafifletmek için elinden geleni yaparak evdeki sorumluluklarını yerine getirmeye çalıştı.\nZehra, sadece Allah’a (cc) karşı olan sorumluluklarına değil çevresindeki insanlara karşı\nolan sorumluluklarına da dikkat etmeye başladı. Annesine daha fazla yardımcı oluyordu,\narkadaşlarına karşı daha sabırlı ve anlayışlı davranıyordu. Kendi davranışlarını gözden ge-\nçirdikçe çevresine olan tutumunda da değişiklikler olmaya başladı. Bu durum, ailesinin ona\nolan güvenini artırdı ve Zehra da hayatındaki güzel değişimleri görmeye başladı.\nZehra genç sahabilerin hayatını örnek alarak başladığı bu yolculukta her küçük adımın as-\nlında büyük bir anlam taşıdığını fark etti. Sorumluluklarını yerine getirdikçe Allah’a (cc), ai-\nlesine ve çevresine olan sorumluluklarını daha derin bir şekilde hissediyor ve gelecekteki\nbüyük sorumluluklara da kendini daha hazır hissediyordu.\n(Kitap için yazar tarafından oluşturulmuştur.)\n1. Zehra’nın sahabileri örnek alarak sorumluluklarının farkına varması, onun hayatında\nne gibi değişikliklere sebep olmuştur? Düşüncelerinizi verilen alana yazınız.\n572. Ünite\nKontrol Noktası\nUygulama adımlarını takip ederek etkinliği tamamlayınız. Hz. Peygamber’in gençlere verdiği\ndeğere ilişkin güvenilir kaynaklardan araştırma yapınız, bulduğunuz örnek olayları inceleyiniz.\nHz. Muhammed’in (sav) gençlere nasıl değer verdiğine ilişkin aşağıda verilen maddelerin altına\nbulduğunuz örnek olayları kısaca yazınız.\nHz. Peygamber,\ngençlerin ihtiyaçlarını gözetmiştir. Örneğin\ngençlere merhametle yaklaşmıştır. Örneğin\ngençlerle fikir alışverişinde bulunmuştur. Örneğin\ngençlere sorumluluk vermiştir. Örneğin\n2.2. Gençlerin Dünyasında Peygamberimiz\nKonuya Başlarken\nHz. Ali’ye, sizler Resulullah’ı nasıl severdiniz, diye sordular. Hz. Ali şunları söy-\nledi: “Vallahi biz; bütün mal varlığımızdan, çocuklarımızdan, babalarımızdan,\nanalarımızdan ve susadığımızda soğuk suya duyduğumuz sevgiden daha çok\nResulullah’ı severdik.”19\n1. Metinden hareketle Hz. Peygamber ile yanında yetişen gençler arasın-\ndaki sevgi ve bağlılık hakkında neler düşünüyorsunuz?\nHz. Muhammed’in (sav) peygamberlik görevini yerine getirdiği döneme Asrısaadet denmekte-\ndir. Kur’an-ı Kerim, o dönemde yaşayan sahabeden “Allah onlardan razı, onlar da Allah’tan\nrazı olmuştur.”20\ndiye bahsetmektedir.\n58Peygamberimizin Çevresindeki Gençler\n3. Etkinlik\nAdı\nAsrısaadet’teki Gençlerin Hz. Peygamber’e Olan Sevgisi\nAmaç Asrısaadet’teki gençlerin Peygamberimize duyduğu sevgiye ait unsurları açıklayabilme\nYönerge: Metinden hareketle soruyu cevaplayınız.\n“Peygamber Efendimiz vefat ettikten sonra Ebu Hüreyre (ra) Medine pazarına gitti ve alışverişle\nuğraşan insanlara şöyle seslendi: ‘Ey çarşı-pazar halkı! Sizi engelleyen şey nedir?’ Onlar ‘Hangi\nkonuda ey Ebu Hüreyre?’ diye sorduklarında şöyle devam etti: ‘Resulullah’ın mirası orada dağı-\ntılırken siz burada duruyorsunuz! Niçin gidip de ondan nasibinizi almıyorsunuz?’ Onlar ‘Nerede?’\ndiye sorunca ‘Mescitte.’ diyerek cevap verdi. İnsanlar adeta koşturarak mescide gittiler. Ebu Hü-\nreyre ise yerinde durdu ve onları bekledi. Döndüklerinde onlara ‘Ne oldu?’ diye sordu. İnsanlar\n‘Ey Ebu Hüreyre! Mescide gittik. İçeriye de girdik. Ancak orada miras olarak dağıtılan herhangi\nbir şey göremedik!’ dediler. Ebu Hüreyre ise ‘Mescitte kimseyi görmediniz mi?’ diye tekrar sordu.\nOnlar ‘Evet! Bir grubun namaz kıldığını, diğer bir topluluğun Kur’an okuduğunu, başka bir grubun\nda helal ve haram meselelerini müzakere ederek ilimle meşgul olduklarını gördük!’ dediler. Bunun\nüzerine Ebu Hüreyre şöyle dedi: ‘Hâlâ anlamıyor musunuz? İşte Hz. Muhammed’in (sav) asıl\nmirası zaten budur!’ ”\n(Heysemi, Mecmau’z-Zevaid, 2/30)\nAsrısaadet’teki gençlerden biri olan Ebu Hüreyre (ra), tüm sahabiler gibi Peygamber Efendimiz’e\nolan sevgi ve saygısını onun vefatından sonra da devam ettirmiştir. Ona olan vefa ve sa-\ndakatini Hz. Muhammed’in (sav) Kur’an, namaz, ilim gibi manevi miraslarına sahip çıkarak\ngöstermiştir.\n1. Asrısaadet’teki gençlerin, Peygamber Efendimiz’e vefa ve sadakatle bağlı kalmasının\nsebepleri nelerdir? Düşüncelerinizi verilen alana yazınız.\n10 dk.\nDeğerlendirme: Etkinliği değerlendirmek için karekodu okutunuz.\n592. Ünite\nşehadet\nKendisinden\ntanıklık istenen\nkişinin görmüş\nolduğu bir\nolayı Allah’ın\nhuzurunda\nbulunuyor gibi\nbir duyguyla\ndosdoğru haber\nvermesi, şahitlik\nyapması. (Serinsu\nvd., “şehadet”, 338)\nGenç bir sahabi olan Muaz bin Cebel (ra), Sevgili Peygamberimizin\nyanında yolculuk yapıyordu. Peygamber Efendimiz ona “Ey Muaz!”\ndiye seslendi. Hz. Muaz hemen “Buyur ya Resulallah! Emrine amade-\nyim!” diye karşılık verdi. Hz. Peygamber, ona iki kere daha bu şekilde\nseslendi ve başka bir şey söylemeden bekledi. Böylece onun dikkatini\ntoplamak istedi. İyice meraklanan Hz. Muaz, Sevgili Peygamberimizin\nsöyleyeceklerine kulak kesildi. Ne söyleyecek diye pürdikkat onu iz-\nlemeye başladı. Sonunda Sevgili Peygamberimiz şöyle buyurdu:\n“Kim, kalbiyle tasdik ederek Yüce Allah’tan başka ilah olmadığına ve\nHz. Muhammed’in Allah’ın Resulü olduğuna şehadet ederse Allah\nona cehennemi haram kılar.”21\n“Şehadet” kavramı bir şeyin doğruluğuna inanmak manasında kul-\nlanılmıştır. Şehadet kavramı aynı zamanda tanıklık etmek mana-\nsına da gelir ki buna “şahitlik etmek” deriz. Öyleyse bizler “kelime-\nişehadet” getirdiğimizde hem Yüce Allah’tan başka ilah olmadığına,\nHz. Muhammed’in (sav) O’nun kulu ve elçisi olduğuna şahitlik ediyor\nhem de bunun doğruluğuna inandığımızı açıklamış oluyoruz. Yine bu\nsebeple Allah (cc) yolunda savaşarak ölenlere de “şehit” diyoruz. Çün-\nkü şehitlerimiz, Yüce Allah’ın varlığı ve birliği yönündeki şehadetlerini\ncanlarını feda ederek göstermiş olurlar. Böylece onlar en büyük şahit-\nliği yapmaktadırlar.\nTANIM\nTERİM ANLAM\nTanıklık etme, şahit olma, Allah (cc)\nyolunda cihat ederken şehit olma\nBir kişinin Allah’ın (cc) birliğini ve\nHz. Muhammed’in (sav) O’nun kulu ve\nelçisi olduğunu dile getirmesi\nŞEHADET\n“Rabbimiz! İndirdiğine inandık ve\npeygambere tabi olduk. Artık bizi şehadet\nedenlerle beraber yaz.”22\n“... Allah yolunda cihad edin. Bilirseniz,\nbu sizin kendi iyiliğinizedir.”23\nAYET ÖRNEĞİ\n1. Şehadet edecek kişinin doğru sözlü\nolması\n2. Şehadetin manasını biliyor olması\n3. Şehadeti, samimi ve içten bir şekilde\nkabul ederek söylemesi\n4. Şehadet getirecek kişinin akıllı olması\nŞARTLARI\nBilgi Görseli 2.2: Şehadet kavramının Frayer (Freye) tekniği ile gösterimi\n60Peygamberimizin Çevresindeki Gençler\nGörsel 2.4: Hz. Peygamber’in evinin ve mescidinin bulunduğu yer olan Mescid-i Nebevi’nin ilk şekli\n(Temsilî)\nİslam’ın temel kaynağı olan Kur’an-ı Kerim’i ancak Hz. Peygamber’in\nsözleri ve davranışları sayesinde anlayabilir, hayatımıza uygulayabili-\nriz. Çünkü o, ayetleri açıklamış ve hayatında uygulamıştır. Yüce Allah\nKur’an’da “Namazı kılın, zekâtı verin.”24\nbuyurur ancak namazın kaç\nrekât olduğunu ve nasıl kılınacağını, hangi maldan ne kadar zekât ve-\nrileceğini bize Sevgili Peygamberimiz öğretmiştir.\nYüce Allah, onu âlemlere rahmet olarak göndermiştir25 (Görsel 2.4).\nHz. Peygamber’in sevgisi bütün insanlığı içine alacak kadar büyük­\ntü. Kendisini örnek almamız gereken ve bizi böylesine seven Sevgili\nPeygamberimiz, kendisine yakın olabilmemiz konusunda ise şöyle bir\nmüjde vermiştir:\n“Kıyamet gününde insanların bana en yakın olanı üzerime en çok\nsalatüselam okuyanıdır.”26\n61\nŞehadet kavramıyla\nilgili e-içeriğe ulaşmak\niçin kare­kodu okutunuz.2. Ünite\ncihat\nAllah yolunda\nsavaşmaktır.\nAynı zamanda\nİslam’ın bilinmesi,\nyaşanması,\ntanınması ve\nyüceltilmesi\niçin gayret\ngöstermektir.\n(Serinsu vd., “cihat”,\n50)\nUrve bin Mesud (ra), sahabenin Hz. Peygamber’e olan sevgisini şöy-\nle anlatmaktadır: “Yüce Allah’a yemin ederim ki ben birçok kralın hu-\nzuruna çıktım; heyet içerisinde Kayser’e, Kisra’ya ve Necaşi’ye git-\ntim. Vallahi, Hz. Muhammed’in (sav) ashabının ona saygı gösterdiği\nkadar hiçbir krala adamlarının saygı gösterdiğini görmedim. Öyle ki\nHz. Muhammed (sav), sahabilerine bir şey emredince o emri yerine\ngetirmek için hemen koşuşturuyorlar! Konuştuğu zaman sahabileri\nseslerini onun yanında iyice alçaltıyorlar! Ona çok saygı duyuyorlardı.”27\nSahabilerin Sevgili Peygamber’e olan vefa ve sadakatini gören Urve bin\nMesud (ra), sonraki süreçte bu durumdan etkilenip Müslüman olmuştur.\nSevgili Peygamberimiz genç sahabilerin kişilik özelliklerini çok iyi bildi-\nği için onlara uygun görevler vermiş, görevlerinde başarılı olmaları için\nonları teşvik etmiştir (Görsel 2.5). Genç sahabiler de ona itaat etme\nkonusunda çok dikkatli davranmışlardır. Hz. Peygamber’in emirlerini\nyerine getirmişler ve onunla birlikte mücadele etmekten geri durma-\nmışlardır. Onlar, cihat etme ve Allah (cc) uğrunda şehit olma gayesiyle\nyaşamışlardır. Nitekim Hz. Peygamber şöyle buyurmuştur: “Kim içten-\nlikle Allah’tan şehit olmayı dilerse yatağında bile ölse Allah onu şehitle-\nrin makamlarına ulaştırır.”28\nBu hadisten anlaşıldığı üzere cihadın farklı\nyönleri de bulunmaktadır.\nBir Hadis\ntebliğ\nPeygamberlerin,\nAllah’ın kendilerine\nindirmiş olduğu\nvahiyleri insanlara\neksiksiz olarak\nbildirmesidir.\n(Serinsu vd., “tebliğ”,\n354)\nGörsel 2.5\nİnsanların\nyeteneklerine göre\nyetiştirilmesi başarıyı\nberaberinde getirir.\nHz. Peygamber, şöyle buyurmuştur: “(Asıl) Cihad, kişinin kendi\nnefsiyle (kötü arzu ve istekleriyle) olandır.”\n(Tirmizi, “Fedailü’l-Cihad”, 2)\nGenç sahabiler, cihadın yalnızca savaş meydanlarında gerçekleşme-\ndiğini bilirlerdi. Onlara göre tebliğ, insanları hakka davet etmek ve İs-\nlam’ın güzelliklerini anlatmak gibi önemli bir cihat yöntemiydi. Bu bilinçle\nhareket eden sahabiler, tebliğ faaliyetlerine büyük önem vermiştir.\nAsrısaadet’teki genç-\nlerin Hz. Peygamber’e\nsevgi ve bağlılığını\ngösterme yollarıyla\nilgili e-içeriğe ulaşmak\niçin karekodu okutunuz.\n62Peygamberimizin Çevresindeki Gençler\n4. Etkinlik\nAdı\nSevginin Etkileri\nAmaç Asrısaadet gençlerinin Hz. Peygamber’e duydukları sevgiyi çözümleyebilme\nYönerge: Metinleri okuyunuz ve metinlerden hareketle soruları cevaplayınız.\nNamaz, Mekke’de farz kılınmıştır. Müslümanlar Medine’ye hicret ettikten sonra\ninsanların namaza nasıl çağrılacağı ilk başta belirlenmemiştir. Hz. Peygamber bu\nkonuda herkesin fikrini almıştır. Sahabilerden bazıları insanların namaza çan çala-\nrak, bazıları boruya üfleyerek, bazıları da ateş yakarak çağrılması teklifinde bulun-\nmuştur. Hz. Peygamber, bu teklifleri başkalarının âdetleri olduğu için reddetmiştir.\nBazı sahabiler ise rüyalarında ezan sözlerini işittiklerini Peygamber Efendimiz’e an-\nlatmışlardır. Bunun üzerine Peygamber Efendimiz Müslümanların ezanla namaza\nçağrılmasına karar vermiştir. Hz. Peygamber, ezan okuması için de Hz. Bilal’i gö-\nrevlendirmiştir.29\nİbni Abbas (ra) Hz. Peygamber’den bir şeyler öğrenmek için sürekli onun\nyanında bulunmaya çaba göstermiştir. İbni Abbas’ın (ra) bu gayretini gören\nSevgili Peygamberimiz “Allah’ım onu dinde anlayış sahibi kıl, ona hikmeti\nöğret.” diye dua etmiştir. Hz. Peygamber’in bu duası, kendisini yetiştirmesi\nkonusunda İbni Abbas’ı teşvik etmiştir. Hz. Peygamber’den sonra da bilgi ve\nzekâsı ile insanları yönlendiren İbni Abbas (ra), Kur’an’ın çevirmeni anlamı-\nna gelen “Tercümânü’l Kur’ân” olarak anılmıştır.30\nAbdullah bin Amr (ra) anlatıyor: “Bir sahabi Hz. Peygamber’e geldi ve cihada\nkatılmak için izin istedi. Hz. Peygamber ise ona ‘Senin annen baban var mı?’\ndiye sordu. Adam ’Evet, var.’ deyince ‘Öyleyse sen onlara hizmet ederek\ncihat et.’ buyurdu.”31\n1. Asrısaadet’teki gençlerin İslam için vermiş oldukları mücadelede Hz. Peygamber’e duy-\ndukları sevginin etkisini açıklayınız.\n2. Hz. Peygamber’e duyduğunuz sevgi ve saygıyı göstermek için günlük hayatta sizler\nneler yapıyorsunuz? Düşüncelerinizi aşağıdaki alana yazınız.\n10 dk.\nDeğerlendirme: Etkinliği değerlendirmek için karekodu okutunuz.\n632. Ünite\nKontrol Noktası\nSoruların cevaplarını boş bırakılan alanlara yazınız.\n1. Peygamber Efendimiz’in hangi özellikleri sahabilerin ona sevgiyle bağlı olmasında et-\nkili olmuştur?\n2. Sahabiler, Hz. Peygamber’e olan sevgi ve bağlılıklarını nasıl ifade etmişlerdir?\n2.3. Peygamberimizin Yanında Yetişen Gençler\nKonuya Başlarken\nİnsanlar yeni şeyler öğrenmek veya bir alanda kendilerini yetiştirmek istediklerinde\ngenellikle bir rehbere ihtiyaç duyarlar. Örneğin bugün çok başarılı bir mühendisi\ndüşünelim. Bu mühendis doğru bir şekilde yönlendirilmemiş olsaydı sahip olduğu\nbaşarıya ulaşabilir miydi? Sevgili Peygamberimiz de insanlara doğru yolu göster-\nmesi için gönderilmiş bir rehberdir. Onun rehberliğinde yetişen sahabiler de öğren-\ndiklerini hayata geçirerek başka insanlara yol göstermiştir.\n1. Metinden yola çıkarak insanların Hz. Peygamber’in rehberliğine ne-\nden ihtiyaç duymuş olabileceğini düşününüz. Fikirlerinizi paylaşınız.\n2. Hz. Peygamber’in rehberliğinde yetişen gençler, ondan öğrendikle-\nriyle diğer insanlara hangi amaçla rehberlik etmiştir? Düşüncelerinizi\npaylaşınız.\n64Peygamberimizin Çevresindeki Gençler\nİnsanı iyiye, güzele ve doğruya çağıran İslam’ın davetine koşanların\nçoğu gençlerden oluşmuştur. Hz. Peygamber’in insanları karanlıktan\naydınlığa çıkaran mesajına en çok gençler ilgi göstermiş ve ona des-\ntek olmuşlardır. Sevgili Peygamberimiz, anlattığı mesajı hayatında uy-\ngulayan en güzel örnekti.\nGençlerin Müslüman olmasına büyük önem veren Peygamber Efendimiz,\ngençlerle çok yakın arkadaşlıklar kurmuştur. Onlara sorumluluk ver-\nmiş ve onları sorunun değil çözümün bir parçası olmaya çağırmıştır.\nHz. Peygamber gençlerle vakit geçirmiş, onlara ikramda bulunmuş ve\ndavetlerine icabet etmiştir. Onların gayretlerini takdir etmiş, onları ye-\nteneklerine göre yönlendirmiştir. Hz. Peygamber’in bu özelliği gençle-\nrin ona ilgi göstermesinin en önemli sebeplerindendi. Gençlerin akın\nakın Müslüman olmasının arka planında Hz. Peygamber’in onlara ver-\ndiği kıymet vardır.\nHz. Abdullah bin Mesud\nHz. Ali\nHz. Erkam bin Ebülerkam\nHz. Fatıma\nHz. Fatıma (Hz. Ömer’in kardeşi)\nHz. Muhammed (sav)\nBilgi Görseli 2.3: Hz. Peygamber’e ilk iman eden sahabilerin çoğu gençlerden oluşmuştur.\nCahiliye Dönemi’nde yaşanan olaylar toplumun büyük bir kesimini\nolumsuz etkilemiştir. Adaletin uygulanmadığı ve insana gereken de-\nğerin verilmediği bu toplumda haksızlıklar artmış ve kötülükler yay-\ngınlaşmıştır. Bu durum ise insanların çaresiz ve mutsuz bir şekilde\nyaşamalarına sebep olmuştur. Yaşanan bu olumsuzluklardan en çok\netkilenenler ise dönemin çocukları ve gençleriydi.\nAdaletsiz bir topluma peygamber olarak gönderilen Hz. Muhammed (sav),\ntoplumun yanlış yönlerini insanlara anlatmıştır. O; insanlığı, bir olan\nAllah’a (cc) inanmaya ve Cahiliye Dönemi’nin yaygın kötülüklerine bu-\nlaşmadan İslam’a uygun bir hayat yaşamaya davet etmiştir. Bu davet,\nen çok da toplumun yanlışlarından rahatsız olan gençlerin dikkatini\nçekmiştir. Cahiliye toplumu onlara sorgulamayı yasaklamış ve düze-\nnin asla değişmeyeceğini söylemiştir. Sevgili Peygamberimiz ise on-\nları sorgulamaya teşvik etmiş ve İslam inancı sayesinde daha güzel\nbir toplum olunabileceğini savunmuştur. Hz. Peygamber’in tebliğini\ndinleyen gençler, toplumun yanlışlarını sorgulamaya, sorguladıkça da\ntoplum tarafından büyük bir baskı görmeye başlamışlardır.\n65\nHz. Musab bin Umeyr\nHz. Rukiye\nHz. Ümmü Gülsüm\nHz. Zeyneb\nHz. Zeyd bin Harise2. Ünite\nBirçok genç, Sevgili Peygamberimizin tebliğini kabul etmiş ve onun\netrafında kenetlenmeye başlamıştır. Büyük bir cesaretle inançlarını\nçevresindekilere ifade etmişlerdir. Bu kararlı duruştan etkilenen insan-\nlar da toplumdaki yanlış inanışları sorgulamaya başlamıştır. Toplum-\ndaki bu uyanıştan rahatsız olan müşrikler, sahabilere çeşitli baskılar\nyapmış fakat bu baskılar genç sahabeyi yıldıramamıştır. Peygamber\nEfendimiz’in yönlendirmesiyle Müslüman bir grup Habeşistan’a hicret\netmişti (Görsel 2.6). Hz. Peygamber, bu grubun liderliğine Cafer bin\nEbu Talib’i (ra) getirmiştir. Cafer bin Ebu Talib (ra), doğup büyüdüğü\ntopraklardan ayrılırken genç yaşında büyük bir kafilenin de sorumlulu-\nğunu almıştır.32\nGörsel 2.6: Müslümanlar, inançlarını özgürce yaşayabilmek için hicret etmek zorunda kalmıştır.\nMüslümanların Habeşistan’a hicret etmesinden rahatsız olan müşrik-\nler, Habeşistan Kralı Necaşi’ye bir elçi göndermiştir. Elçi, Müslüman-\nları kendilerine teslim etmesi konusunda Necaşi’yi ikna etmeye ça-\nlışmıştır. Necaşi’nin huzuruna çıkan Cafer bin Ebu Talib (ra) her şeyi\ngöze alarak inancını savunmuş ve İslam’ı tebliğ etmiştir. Cafer bin Ebu\nTalib’in (ra) tebliğinden etkilenen Necaşi, Mekkeli müşriklerin istekleri-\nni reddetmiş ve Müslümanları ülkesinde ağırlamaya devam etmiştir.33\n66Peygamberimizin Çevresindeki Gençler\nOkuma Metni\nMetinden hareketle soruları cevaplayınız.\nCafer bin Ebu Talib (ra) İslam’ı Anlatıyor\nMüslüman heyeti, Habeşistan Kralı Necaşi’nin huzuruna çıktığı zaman Necaşi onlara İslam’ı\nneden seçtiklerini sordu. Heyetin temsilcisi olan Cafer bin Ebu Talib (ra) ise ona şu şekilde\ncevap verdi: “Ey hükümdar! Biz cahilce yaşayan bir toplumduk. Putlara tapar ve her türlü kö-\ntülüğü yapardık. Akrabalık bağına riayet etmezdik. Komşularımıza ve himayemiz altındakile-\nre kötü davranırdık. İçimizdeki güçlüler, zayıflarımızı ezerdi. Sonra Yüce Allah bize aramız-\ndan; soyunu, doğruluğunu, güvenilirliğini ve iffetini yakından tanıdığımız bir resul gönderdi.\nBu resul bizleri Allah’ın birliğine, O’na hiçbir şeyi ortak koşmamaya ve taptığımız putları terk\netmeye davet etti. O; bizlere doğru sözlü olmayı, emaneti sahibine vermeyi, akrabalık bağını\ngözetmeyi, komşuluğu ve birlik olmayı, haramlardan ve kan dökmekten uzak durmayı öğret-\nti. Bizi kötülüklerden, yalan sözden, yetim malı yemekten alıkoydu. Bize, namaz kılmayı ve\noruç tutmayı emretti. (…) Bunun üzerine biz de ona iman ettik. Onun dediğini doğru bulduk\nve kabul ettik. Bize haram kıldığı şeyleri haram, helal kıldığı şeyleri de helal saydık. Son-\nrasında ise kavmimiz bize saldırdı. Bize işkence yaptılar, tekrar putlara tapmamız için bizi\ndinimizden döndürmek istediler. Bize zulmettiklerinde ve dinimizi yaşamamıza engel olduk-\nlarında senin ülkene gelmek için yola çıktık. Başka ülkelere gitmek yerine seni tercih ettik.\nEy hükümdar! Bunu yaparken senin yanında zulme uğramamayı ümit ettik!”\n(İbni Esir, el-Kâmil fi’t-Tarih, 1/677)\n(Kısaltılmıştır.)\n1. Sizce Cafer bin Ebu Talib (ra), İslam’ın hangi yönlerinden etkilenerek Müslüman ol-\nmuştur?\n2. Cafer bin Ebu Talib’in (ra) mücadelesini örnek alan bir genç olarak hayatınızda karşı-\nlaştığınız zorluklarla mücadele etme yöntemleriniz nelerdir? Bir örnekle anlatınız.\n672. Ünite\n5. Etkinlik\nAdı\nAmaç\n5N1K\nHz. Peygamber’in yanında yetişen gençlerin onu rehber edinmesi hakkında sorular\nsorabilme\nYönerge: 5N1K sorularını cevaplayınız.\n5N1K\nKİM?\nPeygamber Efendimiz\nHabeşistan’a hicret edecek\nkafilenin liderliğini kime\nvermiştir?\nNE?\nGenç sahabilerin\nHz. Peygamber’i örnek\nalmasında etkili olan\nözellikler nelerdir?\n10 dk.\nNASIL?\nSevgili Peygamberimiz,\ngençlere nasıl\nörnek olmuştur?\nNE ZAMAN?\nSevgili Peygamberimiz,\ngençlerle ne zaman\nistişare etmiştir?\nNEREDE?\nGençler, Hz. Peygamber’in\nkendilerine örnek\naldıkları özelliklerini\nnerede kullanmışlardır?\nNİÇİN?\nGenç sahabiler,\nyaşamları boyunca\nniçin Hz. Peygamber’i\nörnek almıştır?\nDeğerlendirme: Karekoddaki öz değerlendirme formunu doldurunuz.\n68Peygamberimizin Çevresindeki Gençler\nHz. Muhammed’in (sav) tebliğinden etkilenen gençler insanları İslam’a\ndavet etme görevinde ona destek olmuşlardır. Genç sahabilerin bu\ndesteği, İslam’ın yayılmasına büyük katkıda bulunmuştur. Musab bin\nUmeyr’in (ra) İslam’ın tebliğindeki rolü bunun en güzel örneklerinden\nbiridir. O, İslam’ı kabul etmesinden sonra çeşitli baskılar görmüştür.\nBaskılara ve tehditlere boyun eğmemiş, sahip olduğu bütün imkân-\nlardan İslam için vazgeçmiştir. Musab bin Umeyr (ra), inancına her\nzaman bağlı kalmış ve İslam’ı anlatma konusunda büyük bir özveri\nsergilemiştir. Onun sahip olduğu bu özelliklerinin farkında olan Sevgili\nPeygamberimiz, Musab bin Umeyr’i (ra) bir davetçi olarak Medine’ye\ngöndermiştir. Böylece Medine hicrete hazır hâle getirilmiştir. O, Me-\ndinelilere İslam’ı anlatmış ve onların Müslüman olmalarına vesile ol-\nmuştur. Musab bin Umeyr (ra), bu yönüyle İslam’ın ilk öğretmeni kabul\nedilmiştir.34\nEtkileşimli 5N 1K bilgi\ngörseline ulaşmak için\nkarekodu okutunuz.\nAnlattıklarını önce kendi\nyaşamaya dikkat ederek\nKarşılaştığı engellere rağmen\nmücadeleyi bırakmayarak\nAllah’tan (cc) aldığı vahyi\ninsanlara eksiksiz bir şekilde\nulaştırarak\nHz. Peygamber’in\ngençlere rehber olma\nmodeli\nİnsanlara karşı\nkibar davranarak\nİnsanlar arasında ayrım\nyapmayarak\nİnsanlara karşı\nsabırlı ve merhametli olarak\nBilgi Görseli 2.4: Hz. Peygamber gençlere rehber olmuştur.\n692. Ünite\nGörsel 2.7\nGenç sahabiler,\nİslam’ı anlatmak için\ntebliğ faaliyetlerinde\nbulunmuştur.\nGörsel 2.8\nMüslümanlar,\nsahabeden duydukları\nHz. Peygamber’in\nhadislerini gelecek\nnesillere aktarmışlardır.\nHz. Peygamber’in sabırlı ve mücadeleci bir davetçi olma özelliğini ör-\nnek alanlardan biri de kızı Hz. Zeyneb’di. O, Hz. Muhammed’e (sav)\npeygamberlik geldikten sonra ilk iman edenler arasında yer almıştır.\nFakat Hz. Zeyneb’in eşi, toplum baskısından çekinerek iman etmek\nistememiştir. Hz. Zeyneb, eşine rağmen inancından vazgeçmemiştir.\nOnun, eşine karşı sabırlı ve nazik tutumu sonraki dönemlerde eşinin\nMüslüman olmasına vesile olmuştur.35\nGenç sahabiler, Peygamber Efendimiz’i doğ-\nru bir şekilde anlama konusunda büyük gay-\nret göstermişlerdir (Görsel 2.7). Hz. Peygam-\nber’in etrafından ayrılmayan gençler, onun\ndavranışlarını büyük bir titizlikle gözlemle-\nmişlerdir. Gözlemlediklerini hayatlarına da\naktaran genç sahabiler, öğrendiklerini başka\ninsanlara da ulaştırmak için çabalamışlardır.\nGenç sahabilerin bu gayreti İslam’ın dünya-\nya yayılmasında da önemli bir faktör olmuştur\n(Görsel 2.8). Çalışkanlığıyla öne çıkan genç\nsahabilerden biri de Abdullah’tı (ra). O, küçük\nyaşından itibaren Sevgili Peygamberimizin\nyanında bulunmuştur. Abdullah bin Ömer\n(ra), Hz. Peygamber’in sözlerini anlamaya\nçalışmış; hâl ve hareketlerini gözlemlemiştir.\nHz. Peygamber’i her konuda örnek alan Ab-\ndullah bin Ömer (ra), onun davranışlarını ve\nsözlerini önce kendi hayatında uygulamış\ndaha sonra da diğer insanlara iletmiştir. Ab-\ndullah bin Ömer (ra), en çok hadis nakleden\nsahabilerden kabul edilmiştir.36\n70Peygamberimizin Çevresindeki Gençler\n6. Etkinlik\nAdı\nMasal Yazıyorum\nAmaç Duygu, düşünce ve değerlerini ifade ederken özgür ve kararlı olma konusunda\nfarkındalık kazanabilme\nYönerge: Giriş kısmı verilen masalın kahramanı olduğunuzu düşünerek devamını yazınız.\nUzak Şehrin Bilge Genci\nZamanın birinde çok uzaklarda bir şehir varmış. Bu şehrin insanları özünde çok iyi insanlarmış\nfakat onları doğruya ve güzele çağıran bir rehberleri olmadığı için iyiliği ve güzelliği bilmez-\nlermiş. Şehirdeki insanlar birbirlerine haksızlıklar yaparmış. Yaşananlar insanlar arasındaki\ngüveni zedelemeye başlamış. İnsanlar bu duruma çok üzülürmüş. Derken bir gün şehre bir\ngenç gelmiş. Bu genç, şehirdeki diğer insanlara hiç benzemezmiş. Genç, şehirde yaşamaya\nbaşlamış ama şahit olduğu haksızlıklar gencin canını sıkmış. Düşünmüş taşınmış ve şehirdeki\ninsanlara doğru ve güzeli öğretmeye, haksızlıklarla mücadele etmeye karar vermiş.\n(Kitap için yazar tarafından oluşturulmuştur.)\n15 dk.\nDeğerlendirme: Karekoddaki öz değerlendirme formunu doldurunuz.\nPeygamber Efendimiz’in çok yönlü bir kişiliği vardı. Sevgili Peygamberimiz\nİslam’ı tebliğ etme, devlet başkanı ve ordu komutanı olma görevleriyle de\ninsanlar için en güzel örnek olmuştur. Kendini diğer insanlardan üstün gör-\nmemiştir. Yapılacak işlerle ilgili arkadaşlarıyla fikir alışverişinde bulunmuştur.\n712. Ünite\nÜnite kavram oyununa\nulaşmak için karekodu\nokutunuz.\nSahabiler, Hz. Peygamber’le savaşlara katılmıştır. Savaşlar sırasın-\nda Sevgili Peygamberimiz sahabilere farklı görevler vermiştir. Örneğin\nHz. Ali ve Musab bin Umeyr’e (ra) sancak tutma,37\nbazı genç sahabiye\nde ordu komutanlığı görevini vermiştir. Orduda Üsame bin Zeyd’den\n(ra) yaşça büyük sahabiler olmasına rağmen Sevgili Peygamberimiz,\nyaştan ziyade liderlik kabiliyetine önem vermiştir. Bu sebeple Usame\nbin Zeyd’i (ra) henüz on sekiz yaşındayken ordu komutanı yapmıştır.\nYönetim konusunda yetenekli olan sahabilerden Attab bin Esid’i (ra)\nMekke’de kadı olarak görevlendirmiştir.38\nHz. Peygamber’in liderliğinde çeşitli görevler üstlenen sahabiler,\nbu sorumlulukları büyük bir onur ve sadakatle yerine getirmişlerdir.\nSevgili Peygamberimiz tarafından bir göreve layık görülmek, sahabiler\niçin büyük bir şeref sayılmıştır. Bu sahabilerden biri de okçulukta ye-\ntenekli olan Rafi bin Hadic’di (ra) (Görsel 2.9). O, genç yaşına rağmen\nHz. Peygamber’in takdirini kazanarak orduya kabul edilmiş ve görevini\nbaşarıyla yerine getirmiştir.39\nGörsel 2.9\nHz. Peygamber,\ngençlerin yeteneklerine\ngöre yetiştirilmesini\nteşvik etmiştir. (Temsilî)\nSahabiler; kadın, erkek, genç ve çocuk demeden İslam’ın yayılma-\nsı ve yaşanması için verilen mücadelede daima Hz. Peygamber’in\nyanında yer almışlardır. Bu mücadeleci hanım sahabilerden biri de\nNesîbe (ra) idi. Çevresindeki insanları İslam’a davet etmek için büyük\nbir gayret gösteren Nesîbe (ra), bu çabasını hayatının her alanında\nsürdürmüştür. Bunun en güzel örneklerinden biri de Uhud Savaşı’nda\nsergilediği kahramanlıktır. Bu savaş sırasında eşi ve oğlu ile Resulullah’a\nsiper olmuş, Hz. Peygamber’in yanından hiç ayrılmamış ve onu ko-\nrumak uğruna yaralar almıştır. Resulullah, o gün hangi yöne dönse\nNesîbe’nin (ra) kendisini korumak için savaştığını görmüş ve onun bu\nhareketinden övgüyle bahsetmiştir.40\n72Peygamberimizin Çevresindeki Gençler 7. Etkinlik Adı Amaç Empati Kuruyorum\nHz. Peygamber’in yanında yetişen gençlerin onu rehber edinmeleri konusunda sorgulamalar yapabilme\nYönerge: Metinden yola çıkarak size yöneltilen ifadeleri tamamlayınız.\nMusab bin Umeyr (ra), genç yaşında Müslüman olmuştu. Ailesi ise Musab’ın (ra) Müslüman olmasından rahatsız olduğu için Peygamber Efendimiz’le görüşmesini istemiyordu. Bundan dolayı Musab bin Umeyr (ra), Hz. Peygamber’i gizlice ziyaret etmeye başladı. Ailesi onu dininden döndürmek için çok çaba gösterdi. Hatta onu hapsettiler. Fakat o, ailesinin tüm engellemelerine karşı dininden dönmedi. Varlıklı bir hayat sürerken zorluklarla geçen bir hayatı tercih etti.\n",
    "steps": [
      {
        "title": "Rehberin İzinde Genç Kahramanlar page 0001",
        "type": "visual",
        "imageUrl": "https://firebasestorage.googleapis.com/v0/b/tamuyum.firebasestorage.app/o/imageLibrary%2FMYZ210AYLDPf8TY1yjLnpfWPqZ33%2F1766254913905-Rehberin_%C4%B0zinde_Gen%C3%A7_Kahramanlar_page-0001.jpg?alt=media&token=f125ac6f-16d3-4260-b487-1d1e169e9d44"
      },
      {
        "imageUrl": "https://firebasestorage.googleapis.com/v0/b/tamuyum.firebasestorage.app/o/imageLibrary%2FMYZ210AYLDPf8TY1yjLnpfWPqZ33%2F1766254913906-Rehberin_%C4%B0zinde_Gen%C3%A7_Kahramanlar_page-0002.jpg?alt=media&token=551dd6bc-744f-4117-ab20-b72569883aa7",
        "title": "Rehberin İzinde Genç Kahramanlar page 0002",
        "type": "visual"
      },
      {
        "title": "Rehberin İzinde Genç Kahramanlar page 0003",
        "type": "visual",
        "imageUrl": "https://firebasestorage.googleapis.com/v0/b/tamuyum.firebasestorage.app/o/imageLibrary%2FMYZ210AYLDPf8TY1yjLnpfWPqZ33%2F1766254913894-Rehberin_%C4%B0zinde_Gen%C3%A7_Kahramanlar_page-0003.jpg?alt=media&token=f547839e-cb90-49de-8b18-caaadbf7e99b"
      },
      {
        "title": "Rehberin İzinde Genç Kahramanlar page 0004",
        "type": "visual",
        "imageUrl": "https://firebasestorage.googleapis.com/v0/b/tamuyum.firebasestorage.app/o/imageLibrary%2FMYZ210AYLDPf8TY1yjLnpfWPqZ33%2F1766254913897-Rehberin_%C4%B0zinde_Gen%C3%A7_Kahramanlar_page-0004.jpg?alt=media&token=648d8a6c-1cb4-4a18-a5af-25df048c07be"
      },
      {
        "type": "visual",
        "title": "Rehberin İzinde Genç Kahramanlar page 0005",
        "imageUrl": "https://firebasestorage.googleapis.com/v0/b/tamuyum.firebasestorage.app/o/imageLibrary%2FMYZ210AYLDPf8TY1yjLnpfWPqZ33%2F1766254913898-Rehberin_%C4%B0zinde_Gen%C3%A7_Kahramanlar_page-0005.jpg?alt=media&token=6ab6724c-1c4a-463e-9ef5-aa569812da10"
      },
      {
        "type": "visual",
        "title": "Rehberin İzinde Genç Kahramanlar page 0006",
        "imageUrl": "https://firebasestorage.googleapis.com/v0/b/tamuyum.firebasestorage.app/o/imageLibrary%2FMYZ210AYLDPf8TY1yjLnpfWPqZ33%2F1766254913899-Rehberin_%C4%B0zinde_Gen%C3%A7_Kahramanlar_page-0006.jpg?alt=media&token=9526dd34-4e0a-4a00-baf8-8ac28f3479b6"
      },
      {
        "title": "Rehberin İzinde Genç Kahramanlar page 0007",
        "imageUrl": "https://firebasestorage.googleapis.com/v0/b/tamuyum.firebasestorage.app/o/imageLibrary%2FMYZ210AYLDPf8TY1yjLnpfWPqZ33%2F1766254913899-Rehberin_%C4%B0zinde_Gen%C3%A7_Kahramanlar_page-0007.jpg?alt=media&token=356a3ca9-7912-41b8-970f-0d4b4214d2cf",
        "type": "visual"
      },
      {
        "type": "visual",
        "imageUrl": "https://firebasestorage.googleapis.com/v0/b/tamuyum.firebasestorage.app/o/imageLibrary%2FMYZ210AYLDPf8TY1yjLnpfWPqZ33%2F1766254913900-Rehberin_%C4%B0zinde_Gen%C3%A7_Kahramanlar_page-0008.jpg?alt=media&token=12b6f6a1-4d6e-470c-9493-11c3c8bde637",
        "title": "Rehberin İzinde Genç Kahramanlar page 0008"
      },
      {
        "imageUrl": "https://firebasestorage.googleapis.com/v0/b/tamuyum.firebasestorage.app/o/imageLibrary%2FMYZ210AYLDPf8TY1yjLnpfWPqZ33%2F1766254913901-Rehberin_%C4%B0zinde_Gen%C3%A7_Kahramanlar_page-0009.jpg?alt=media&token=b9920b63-13dc-4ca4-9a70-cbf05d4a9c82",
        "type": "visual",
        "title": "Rehberin İzinde Genç Kahramanlar page 0009"
      },
      {
        "type": "visual",
        "title": "Rehberin İzinde Genç Kahramanlar page 0010",
        "imageUrl": "https://firebasestorage.googleapis.com/v0/b/tamuyum.firebasestorage.app/o/imageLibrary%2FMYZ210AYLDPf8TY1yjLnpfWPqZ33%2F1766254913901-Rehberin_%C4%B0zinde_Gen%C3%A7_Kahramanlar_page-0010.jpg?alt=media&token=3a706981-70fd-4093-8044-37650951de69"
      },
      {
        "imageUrl": "https://firebasestorage.googleapis.com/v0/b/tamuyum.firebasestorage.app/o/imageLibrary%2FMYZ210AYLDPf8TY1yjLnpfWPqZ33%2F1766254913902-Rehberin_%C4%B0zinde_Gen%C3%A7_Kahramanlar_page-0011.jpg?alt=media&token=5d3c1fe5-b6bc-42e1-bf2d-0a06e405e55d",
        "title": "Rehberin İzinde Genç Kahramanlar page 0011",
        "type": "visual"
      },
      {
        "imageUrl": "https://firebasestorage.googleapis.com/v0/b/tamuyum.firebasestorage.app/o/imageLibrary%2FMYZ210AYLDPf8TY1yjLnpfWPqZ33%2F1766254913903-Rehberin_%C4%B0zinde_Gen%C3%A7_Kahramanlar_page-0012.jpg?alt=media&token=d26e7e13-dc29-49cc-aa5c-f3b399e0ad0c",
        "type": "visual",
        "title": "Rehberin İzinde Genç Kahramanlar page 0012"
      },
      {
        "type": "visual",
        "imageUrl": "https://firebasestorage.googleapis.com/v0/b/tamuyum.firebasestorage.app/o/imageLibrary%2FMYZ210AYLDPf8TY1yjLnpfWPqZ33%2F1766254913903-Rehberin_%C4%B0zinde_Gen%C3%A7_Kahramanlar_page-0013.jpg?alt=media&token=47a09107-9a56-4f78-85af-5651249bb37b",
        "title": "Rehberin İzinde Genç Kahramanlar page 0013"
      },
      {
        "title": "Rehberin İzinde Genç Kahramanlar page 0014",
        "type": "visual",
        "imageUrl": "https://firebasestorage.googleapis.com/v0/b/tamuyum.firebasestorage.app/o/imageLibrary%2FMYZ210AYLDPf8TY1yjLnpfWPqZ33%2F1766254913904-Rehberin_%C4%B0zinde_Gen%C3%A7_Kahramanlar_page-0014.jpg?alt=media&token=db0386d5-b00c-4174-9f4c-b60b8447c6e3"
      },
      {
        "title": "Rehberin İzinde Genç Kahramanlar page 0015",
        "type": "visual",
        "imageUrl": "https://firebasestorage.googleapis.com/v0/b/tamuyum.firebasestorage.app/o/imageLibrary%2FMYZ210AYLDPf8TY1yjLnpfWPqZ33%2F1766254913905-Rehberin_%C4%B0zinde_Gen%C3%A7_Kahramanlar_page-0015.jpg?alt=media&token=cad82369-ad4e-49d1-86dc-fef93593aadd"
      },
      {
        "type": "htmlSlide",
        "title": "İnteraktif Sunum",
        "content": {
          "categories": [],
          "definition": "",
          "text": "",
          "title": "",
          "term": "",
          "items": []
        },
        "htmlContent": "<!DOCTYPE html>\n<html lang=\"tr\">\n<head>\n    <meta charset=\"UTF-8\">\n    <meta name=\"viewport\" content=\"width=device-width, initial-scale=1.0\">\n    <title>Rehberin İzinde: Genç Bir Kalbin Yolculuğu</title>\n    <script src=\"https://cdn.tailwindcss.com\"></script>\n    <link href=\"https://cdnjs.cloudflare.com/ajax/libs/font-awesome/6.0.0/css/all.min.css\" rel=\"stylesheet\">\n    <style>\n        @import url('https://fonts.googleapis.com/css2?family=Nunito:wght@400;600;700;800&display=swap');\n        \n        body {\n            font-family: 'Nunito', sans-serif;\n            background: linear-gradient(135deg, #f0fdf4 0%, #dcfce7 100%);\n        }\n\n        .card-hover:hover {\n            transform: translateY(-5px);\n            box-shadow: 0 10px 20px rgba(0,0,0,0.1);\n        }\n\n        .game-transition {\n            transition: all 0.3s ease-in-out;\n        }\n\n        .correct-anim {\n            animation: pulse-green 0.5s;\n        }\n\n        .wrong-anim {\n            animation: shake 0.5s;\n        }\n\n        @keyframes pulse-green {\n            0% { transform: scale(1); box-shadow: 0 0 0 0 rgba(34, 197, 94, 0.7); }\n            70% { transform: scale(1.05); box-shadow: 0 0 0 10px rgba(34, 197, 94, 0); }\n            100% { transform: scale(1); box-shadow: 0 0 0 0 rgba(34, 197, 94, 0); }\n        }\n\n        @keyframes shake {\n            0% { transform: translateX(0); }\n            25% { transform: translateX(-5px); }\n            50% { transform: translateX(5px); }\n            75% { transform: translateX(-5px); }\n            100% { transform: translateX(0); }\n        }\n\n        .confetti {\n            position: absolute;\n            width: 10px;\n            height: 10px;\n            background-color: #f00;\n            animation: fall linear forwards;\n        }\n\n        @keyframes fall {\n            to { transform: translateY(100vh) rotate(720deg); }\n        }\n    </style>\n</head>\n<body class=\"min-h-screen text-slate-800 flex flex-col\">\n\n    <!-- Navbar -->\n    <nav class=\"bg-teal-700 text-white p-4 shadow-lg sticky top-0 z-50\">\n        <div class=\"container mx-auto flex justify-between items-center\">\n            <h1 class=\"text-xl md:text-2xl font-bold\"><i class=\"fas fa-compass mr-2\"></i>Rehberin İzinde</h1>\n            <div class=\"text-sm md:text-base bg-teal-800 px-4 py-2 rounded-full font-bold shadow-inner\" id=\"score-display\">\n                Puan: 0\n            </div>\n        </div>\n    </nav>\n\n    <!-- Main Content Area -->\n    <main class=\"flex-grow container mx-auto p-4 flex items-center justify-center\">\n        \n        <!-- MENU SCREEN -->\n        <div id=\"menu-screen\" class=\"w-full max-w-5xl grid grid-cols-1 md:grid-cols-3 gap-8\">\n            <div class=\"col-span-1 md:col-span-3 text-center mb-8\">\n                <h2 class=\"text-3xl md:text-5xl font-extrabold text-teal-800 mb-4\">Genç Bir Kalbin Yolculuğu</h2>\n                <p class=\"text-gray-600 text-lg md:text-xl\">Lütfen başlamak için bir etkinlik seçin:</p>\n            </div>\n\n            <!-- Game Mode 1: Quiz -->\n            <div onclick=\"startGame('quiz')\" class=\"bg-white p-8 rounded-3xl shadow-lg cursor-pointer card-hover border-b-8 border-teal-500 group transition-all\">\n                <div class=\"text-teal-500 text-5xl md:text-7xl mb-6 group-hover:scale-110 transition-transform text-center\">\n                    <i class=\"fas fa-question-circle\"></i>\n                </div>\n                <h3 class=\"text-2xl md:text-3xl font-bold text-center mb-3 text-gray-800\">Liderlik Yolculuğu</h3>\n                <p class=\"text-gray-500 text-center text-base md:text-lg\">Hz. Peygamber ve genç sahabeler hakkında senaryo tabanlı sorular.</p>\n            </div>\n\n            <!-- Game Mode 2: Matching -->\n            <div onclick=\"startGame('match')\" class=\"bg-white p-8 rounded-3xl shadow-lg cursor-pointer card-hover border-b-8 border-orange-500 group transition-all\">\n                <div class=\"text-orange-500 text-5xl md:text-7xl mb-6 group-hover:scale-110 transition-transform text-center\">\n                    <i class=\"fas fa-puzzle-piece\"></i>\n                </div>\n                <h3 class=\"text-2xl md:text-3xl font-bold text-center mb-3 text-gray-800\">Kavram Eşleştirme</h3>\n                <p class=\"text-gray-500 text-center text-base md:text-lg\">İstişare, Tebliğ, Cihat ve Şehadet kavramlarını tanımlarıyla eşleştir.</p>\n            </div>\n\n            <!-- Game Mode 3: Who Am I -->\n            <div onclick=\"startGame('who')\" class=\"bg-white p-8 rounded-3xl shadow-lg cursor-pointer card-hover border-b-8 border-indigo-500 group transition-all\">\n                <div class=\"text-indigo-500 text-5xl md:text-7xl mb-6 group-hover:scale-110 transition-transform text-center\">\n                    <i class=\"fas fa-user-friends\"></i>\n                </div>\n                <h3 class=\"text-2xl md:text-3xl font-bold text-center mb-3 text-gray-800\">Ben Kimim?</h3>\n                <p class=\"text-gray-500 text-center text-base md:text-lg\">İpuçlarından yola çıkarak anlatılan genç sahabeyi bul.</p>\n            </div>\n        </div>\n\n        <!-- QUIZ SCREEN -->\n        <div id=\"quiz-screen\" class=\"hidden w-full max-w-3xl bg-white p-8 md:p-12 rounded-3xl shadow-2xl relative overflow-hidden\">\n            <div class=\"mb-8\">\n                <div class=\"flex justify-between items-center mb-4\">\n                    <span class=\"text-sm md:text-base font-bold text-teal-600 uppercase tracking-wider bg-teal-50 px-3 py-1 rounded-lg\">Soru <span id=\"q-current\">1</span>/<span id=\"q-total\">10</span></span>\n                    <button onclick=\"showMenu()\" class=\"text-gray-400 hover:text-red-500 text-lg transition-colors\"><i class=\"fas fa-times\"></i> Çıkış</button>\n                </div>\n                <div class=\"w-full bg-gray-200 rounded-full h-3 md:h-4\">\n                    <div id=\"progress-bar\" class=\"bg-teal-600 h-3 md:h-4 rounded-full transition-all duration-500\" style=\"width: 0%\"></div>\n                </div>\n            </div>\n\n            <h2 id=\"question-text\" class=\"text-xl md:text-3xl font-bold text-gray-800 mb-8 leading-relaxed\">\n                Soru yükleniyor...\n            </h2>\n\n            <div id=\"options-container\" class=\"space-y-4\">\n                <!-- Options will be injected here -->\n            </div>\n\n            <div id=\"feedback-area\" class=\"hidden mt-8 p-6 rounded-xl bg-blue-50 border-2 border-blue-200\">\n                <p id=\"feedback-text\" class=\"text-blue-900 font-semibold text-lg md:text-xl\"></p>\n                <button onclick=\"nextQuestion()\" class=\"mt-4 bg-teal-600 text-white px-8 py-3 rounded-xl font-bold text-lg hover:bg-teal-700 transition shadow-md w-full md:w-auto\">Devam Et <i class=\"fas fa-arrow-right ml-2\"></i></button>\n            </div>\n        </div>\n\n        <!-- MATCHING SCREEN -->\n        <div id=\"match-screen\" class=\"hidden w-full max-w-6xl bg-white p-8 md:p-10 rounded-3xl shadow-2xl\">\n            <div class=\"flex justify-between items-center mb-8\">\n                <div>\n                    <h2 class=\"text-3xl md:text-4xl font-bold text-gray-800 mb-2\">Kavramları Eşleştir</h2>\n                    <p class=\"text-gray-600 text-lg\">Soldaki kavramı seç, sonra sağdaki doğru tanımıyla eşleştir.</p>\n                </div>\n                <button onclick=\"showMenu()\" class=\"text-gray-400 hover:text-red-500 text-xl p-2\"><i class=\"fas fa-times\"></i></button>\n            </div>\n            \n            <div class=\"grid grid-cols-1 md:grid-cols-2 gap-8 md:gap-12\">\n                <div id=\"terms-container\" class=\"space-y-4 md:space-y-6\"></div>\n                <div id=\"defs-container\" class=\"space-y-4 md:space-y-6\"></div>\n            </div>\n            <div id=\"match-feedback\" class=\"mt-8 text-center font-bold h-8 text-xl text-teal-600\"></div>\n        </div>\n\n        <!-- RESULT SCREEN -->\n        <div id=\"result-screen\" class=\"hidden w-full max-w-2xl bg-white p-12 rounded-3xl shadow-2xl text-center\">\n            <div class=\"mb-6 text-7xl md:text-9xl text-yellow-400 drop-shadow-lg\">\n                <i class=\"fas fa-trophy\"></i>\n            </div>\n            <h2 class=\"text-4xl md:text-5xl font-extrabold text-gray-800 mb-4\">Tebrikler!</h2>\n            <p class=\"text-xl md:text-2xl text-gray-600 mb-8\">Liderlik ve sadakat döngüsünü tamamladın.</p>\n            \n            <div class=\"text-5xl md:text-7xl font-bold text-teal-600 mb-10\" id=\"final-score\">0 Puan</div>\n            \n            <p id=\"result-message\" class=\"text-lg md:text-xl text-gray-500 mb-10 italic bg-gray-50 p-4 rounded-xl\">\n                \"Gençler, kendi potansiyellerine ulaşarak birer lidere dönüşür.\"\n            </p>\n\n            <button onclick=\"showMenu()\" class=\"w-full bg-teal-600 text-white py-4 rounded-2xl font-bold text-xl hover:bg-teal-700 transition shadow-lg hover:shadow-xl transform hover:-translate-y-1\">\n                Ana Menüye Dön\n            </button>\n        </div>\n\n    </main>\n\n    <footer class=\"text-center p-6 text-gray-500 text-sm md:text-base font-medium\">\n        &copy; 2024 Rehberin İzinde İnteraktif Öğrenme Platformu\n    </footer>\n\n    <script>\n        // --- DATA SOURCE ---\n        const quizData = [\n            {\n                question: \"Hz. Peygamber, Ebu Mahzure ezanla alay ettiğinde ona nasıl bir tepki vermiştir?\",\n                options: [\n                    \"Onu cezalandırmış ve şehirden uzaklaştırmıştır.\",\n                    \"Ona kızmış ama affetmiştir.\",\n                    \"Sesini fark edip şefkatle ona ezanı öğretmiştir.\",\n                    \"Onu görmezden gelmiştir.\"\n                ],\n                correct: 2,\n                feedback: \"Doğru! Peygamberimiz ceza yerine potansiyeli görmüş, Ebu Mahzure'ye şefkatle yaklaşarak onu kazanmıştır.\"\n            },\n            {\n                question: \"Al-i İmran suresi 159. ayette Hz. Peygamber'in hangi özelliği vurgulanır?\",\n                options: [\n                    \"Çok ibadet etmesi\",\n                    \"Yumuşak huylu ve merhametli olması\",\n                    \"Savaş stratejilerini iyi bilmesi\",\n                    \"Zengin olması\"\n                ],\n                correct: 1,\n                feedback: \"Ayette 'Sen onlara Allah'ın merhameti sayesinde yumuşak davrandın' buyurulmaktadır.\"\n            },\n            {\n                question: \"Mus'ab bin Umeyr'in lakabı nedir ve Medine'deki görevi neydi?\",\n                options: [\n                    \"Allah'ın Aslanı - Komutan\",\n                    \"İslam'ın İlk Öğretmeni - İslam'ı anlatmak\",\n                    \"Seyfullah - Savaşmak\",\n                    \"Tercüman - Kralla konuşmak\"\n                ],\n                correct: 1,\n                feedback: \"Mus'ab bin Umeyr, konforlu hayatını bırakıp Medine'ye 'İlk Öğretmen' olarak gönderilmiştir.\"\n            },\n            {\n                question: \"Hz. Peygamber ordu komutanı olarak atadığında Üsame bin Zeyd kaç yaşındaydı ve bu neyi gösterir?\",\n                options: [\n                    \"40 yaşındaydı - Tecrübeyi\",\n                    \"25 yaşındaydı - Gücü\",\n                    \"18 yaşındaydı - Liyakat ve yeteneğe verilen önemi\",\n                    \"30 yaşındaydı - Sadakati\"\n                ],\n                correct: 2,\n                feedback: \"Henüz 18 yaşında olmasına rağmen liyakati sebebiyle ordu komutanı olmuştur.\"\n            },\n            {\n                question: \"Habeşistan Kralı Necaşi'nin huzurunda Müslümanları savunan genç sahabi kimdir?\",\n                options: [\n                    \"Hz. Ali\",\n                    \"Mus'ab bin Umeyr\",\n                    \"Cafer bin Ebu Talib\",\n                    \"Zeyd bin Harise\"\n                ],\n                correct: 2,\n                feedback: \"Cafer bin Ebu Talib, Necaşi'ye İslam'ın getirdiği ahlaki güzellikleri anlatan etkileyici bir konuşma yapmıştır.\"\n            },\n            {\n                question: \"Uhud Savaşı'nda Hz. Peygamber'e siper olan ve O'nu korumak için cesurca savaşan kadın sahabi kimdir?\",\n                options: [\n                    \"Hz. Aişe\",\n                    \"Hz. Hatice\",\n                    \"Nesîbe binti Ka'b\",\n                    \"Hz. Fatıma\"\n                ],\n                correct: 2,\n                feedback: \"Nesîbe (ra), Uhud'un en zor anlarında Peygamberimizi koruyan kahramanlardandır.\"\n            },\n            {\n                question: \"'Görüş alışverişinde bulunma, fikir alma ve danışma' anlamına gelen kavram hangisidir?\",\n                options: [\n                    \"Tebliğ\",\n                    \"İstişare\",\n                    \"Cihat\",\n                    \"Tevekkül\"\n                ],\n                correct: 1,\n                feedback: \"Hz. Peygamber ashabıyla sık sık istişare ederdi (Örn: Bedir ve Hudeybiye).\"\n            },\n            {\n                question: \"Kab bin Malik (ra) Tebük Seferi'ne mazeretsiz katılmadığında hatasını nasıl telafi etti?\",\n                options: [\n                    \"Yalan söyleyerek\",\n                    \"Şehri terk ederek\",\n                    \"Dürüstçe hatasını kabul edip tövbe ederek\",\n                    \"Öfkelenerek\"\n                ],\n                correct: 2,\n                feedback: \"Kab bin Malik dürüstlüğü seçti ve bu samimiyeti sayesinde tövbesi kabul edildi.\"\n            }\n        ];\n\n        const whoAmIData = [\n            {\n                question: \"Mekke'nin en zengin ailelerinden birinin çocuğuydum. Her şeyi bıraktım. Medine'ye İslam'ı öğretmek için gittim.\",\n                options: [\"Üsame bin Zeyd\", \"Mus'ab bin Umeyr\", \"Cafer bin Ebu Talib\"],\n                correct: 1,\n                feedback: \"Doğru! Ben Mus'ab bin Umeyr'im.\"\n            },\n            {\n                question: \"On sene Peygamberimize hizmet ettim. Bana bir kere bile 'Öf' demedi. Yaptığım bir şey için 'Niye yaptın?' diye azarlamadı.\",\n                options: [\"Enes bin Malik\", \"Ebu Hüreyre\", \"Abdullah bin Mesud\"],\n                correct: 0,\n                feedback: \"Doğru! Ben Enes bin Malik'im.\"\n            },\n            {\n                question: \"Peygamberimiz beni her gördüğünde gülümserdi, beni hiç kapıdan çevirmedi.\",\n                options: [\"Cerir bin Abdullah\", \"Hz. Ali\", \"Hz. Ömer\"],\n                correct: 0,\n                feedback: \"Doğru! Ben Cerir bin Abdullah'ım.\"\n            },\n            {\n                question: \"Bir tartışmada Bilal'e ten rengiyle hakaret ettim. Peygamberimiz 'Sende cahiliye izi var' deyince çok pişman olup özür diledim.\",\n                options: [\"Ebu Leheb\", \"Ebu Zer\", \"Ebu Cehil\"],\n                correct: 1,\n                feedback: \"Doğru! Ben Ebu Zer'im.\"\n            }\n        ];\n\n        const matchData = {\n            terms: [\n                { id: 't1', text: 'İstişare' },\n                { id: 't2', text: 'Tebliğ' },\n                { id: 't3', text: 'Cihat' },\n                { id: 't4', text: 'Şehadet' }\n            ],\n            defs: [\n                { id: 'd1', text: 'Fikir alışverişinde bulunma, danışma.', match: 't1' },\n                { id: 'd2', text: 'Vahyi insanlara eksiksiz bildirme.', match: 't2' },\n                { id: 'd3', text: 'Allah yolunda her türlü gayret ve mücadele.', match: 't3' },\n                { id: 'd4', text: 'Allah\\'ın birliğine tanıklık etmek ve bu uğurda canı feda etmek.', match: 't4' }\n            ]\n        };\n\n        // --- STATE VARIABLES ---\n        let currentMode = '';\n        let currentIndex = 0;\n        let score = 0;\n        let currentQuestions = [];\n        let selectedTerm = null;\n        let matchedPairs = 0;\n\n        // --- DOM ELEMENTS ---\n        const menuScreen = document.getElementById('menu-screen');\n        const quizScreen = document.getElementById('quiz-screen');\n        const matchScreen = document.getElementById('match-screen');\n        const resultScreen = document.getElementById('result-screen');\n        const scoreDisplay = document.getElementById('score-display');\n\n        // --- CORE FUNCTIONS ---\n\n        function showMenu() {\n            menuScreen.classList.remove('hidden');\n            quizScreen.classList.add('hidden');\n            matchScreen.classList.add('hidden');\n            resultScreen.classList.add('hidden');\n            score = 0;\n            updateScore();\n        }\n\n        function updateScore() {\n            scoreDisplay.innerText = `Puan: ${score}`;\n        }\n\n        function startGame(mode) {\n            currentMode = mode;\n            score = 0;\n            currentIndex = 0;\n            updateScore();\n\n            menuScreen.classList.add('hidden');\n            resultScreen.classList.add('hidden');\n\n            if (mode === 'quiz') {\n                currentQuestions = [...quizData]; // Clone array\n                setupQuiz();\n            } else if (mode === 'who') {\n                currentQuestions = [...whoAmIData];\n                setupQuiz();\n            } else if (mode === 'match') {\n                setupMatch();\n            }\n        }\n\n        // --- QUIZ LOGIC (Used for 'Quiz' and 'Who Am I') ---\n\n        function setupQuiz() {\n            quizScreen.classList.remove('hidden');\n            document.getElementById('q-total').innerText = currentQuestions.length;\n            renderQuestion();\n        }\n\n        function renderQuestion() {\n            const q = currentQuestions[currentIndex];\n            document.getElementById('q-current').innerText = currentIndex + 1;\n            document.getElementById('progress-bar').style.width = `${((currentIndex) / currentQuestions.length) * 100}%`;\n            \n            document.getElementById('question-text').innerText = q.question;\n            const optsContainer = document.getElementById('options-container');\n            optsContainer.innerHTML = '';\n            document.getElementById('feedback-area').classList.add('hidden');\n\n            q.options.forEach((opt, idx) => {\n                const btn = document.createElement('button');\n                btn.className = \"w-full text-left p-4 md:p-6 rounded-xl border-2 border-gray-100 hover:border-teal-500 hover:bg-teal-50 transition-all font-semibold text-gray-700 text-base md:text-lg\";\n                btn.innerText = opt;\n                btn.onclick = () => checkAnswer(idx, btn);\n                optsContainer.appendChild(btn);\n            });\n        }\n\n        function checkAnswer(selectedIdx, btnElement) {\n            const q = currentQuestions[currentIndex];\n            const optsContainer = document.getElementById('options-container');\n            \n            // Disable all buttons\n            Array.from(optsContainer.children).forEach(b => b.disabled = true);\n\n            if (selectedIdx === q.correct) {\n                btnElement.classList.remove('border-gray-100');\n                btnElement.classList.add('bg-green-100', 'border-green-500', 'text-green-800', 'correct-anim');\n                btnElement.innerHTML += ' <i class=\"fas fa-check-circle float-right mt-1\"></i>';\n                score += 10;\n                updateScore();\n            } else {\n                btnElement.classList.remove('border-gray-100');\n                btnElement.classList.add('bg-red-100', 'border-red-500', 'text-red-800', 'wrong-anim');\n                btnElement.innerHTML += ' <i class=\"fas fa-times-circle float-right mt-1\"></i>';\n                \n                // Highlight correct answer\n                const correctBtn = optsContainer.children[q.correct];\n                correctBtn.classList.add('bg-green-100', 'border-green-500', 'text-green-800');\n                correctBtn.innerHTML += ' <i class=\"fas fa-check-circle float-right mt-1\"></i>';\n            }\n\n            // Show feedback\n            document.getElementById('feedback-text').innerText = q.feedback;\n            document.getElementById('feedback-area').classList.remove('hidden');\n        }\n\n        function nextQuestion() {\n            currentIndex++;\n            if (currentIndex < currentQuestions.length) {\n                renderQuestion();\n            } else {\n                endGame();\n            }\n        }\n\n        // --- MATCHING GAME LOGIC ---\n\n        function setupMatch() {\n            matchScreen.classList.remove('hidden');\n            const tContainer = document.getElementById('terms-container');\n            const dContainer = document.getElementById('defs-container');\n            tContainer.innerHTML = '';\n            dContainer.innerHTML = '';\n            matchedPairs = 0;\n            selectedTerm = null;\n            document.getElementById('match-feedback').innerText = '';\n\n            // Randomize definitions\n            const shuffledDefs = [...matchData.defs].sort(() => Math.random() - 0.5);\n\n            matchData.terms.forEach(term => {\n                const div = document.createElement('div');\n                div.id = term.id;\n                div.className = \"p-6 md:p-8 bg-teal-100 rounded-2xl cursor-pointer border-2 border-transparent hover:border-teal-400 font-bold text-xl md:text-2xl text-center shadow-sm transition-all hover:shadow-md flex items-center justify-center min-h-[100px] md:min-h-[120px]\";\n                div.innerText = term.text;\n                div.onclick = () => selectTerm(div);\n                tContainer.appendChild(div);\n            });\n\n            shuffledDefs.forEach(def => {\n                const div = document.createElement('div');\n                div.id = def.id;\n                div.dataset.match = def.match; // Store which term it matches\n                div.className = \"p-6 md:p-8 bg-gray-100 rounded-2xl cursor-pointer border-2 border-transparent hover:border-orange-400 text-lg md:text-xl font-medium flex items-center justify-center text-center shadow-sm transition-all hover:shadow-md min-h-[100px] md:min-h-[120px]\";\n                div.innerText = def.text;\n                div.onclick = () => selectDef(div);\n                dContainer.appendChild(div);\n            });\n        }\n\n        function selectTerm(el) {\n            if (el.classList.contains('opacity-50')) return; // Already matched\n            \n            // Deselect previous\n            if (selectedTerm) selectedTerm.classList.remove('bg-teal-500', 'text-white');\n            \n            selectedTerm = el;\n            selectedTerm.classList.add('bg-teal-500', 'text-white');\n            document.getElementById('match-feedback').innerText = \"Tanımı seçiniz...\";\n        }\n\n        function selectDef(el) {\n            if (!selectedTerm) {\n                document.getElementById('match-feedback').innerText = \"Önce sol taraftan bir kavram seçmelisin.\";\n                return;\n            }\n            if (el.classList.contains('opacity-50')) return;\n\n            if (el.dataset.match === selectedTerm.id) {\n                // Correct Match\n                score += 20;\n                updateScore();\n                \n                selectedTerm.classList.remove('bg-teal-500', 'text-white');\n                selectedTerm.classList.add('bg-green-500', 'text-white', 'opacity-50', 'correct-anim');\n                el.classList.add('bg-green-100', 'border-green-500', 'opacity-50', 'correct-anim');\n                \n                selectedTerm = null;\n                matchedPairs++;\n                document.getElementById('match-feedback').innerText = \"Harika! Doğru eşleştirme.\";\n\n                if (matchedPairs === matchData.terms.length) {\n                    setTimeout(endGame, 1000);\n                }\n            } else {\n                // Wrong Match\n                el.classList.add('bg-red-100', 'wrong-anim');\n                setTimeout(() => el.classList.remove('bg-red-100', 'wrong-anim'), 500);\n                document.getElementById('match-feedback').innerText = \"Yanlış eşleştirme, tekrar dene.\";\n            }\n        }\n\n        // --- END GAME ---\n\n        function endGame() {\n            quizScreen.classList.add('hidden');\n            matchScreen.classList.add('hidden');\n            resultScreen.classList.remove('hidden');\n            \n            document.getElementById('final-score').innerText = score + \" Puan\";\n            \n            if (score > 50) {\n                celebrate();\n                document.getElementById('result-message').innerText = \"Mükemmel! Rehberin izini başarıyla takip ettin.\";\n            } else {\n                document.getElementById('result-message').innerText = \"Güzel deneme! Bilgilerini tazeleyip tekrar deneyebilirsin.\";\n            }\n        }\n\n        function celebrate() {\n            for(let i=0; i<50; i++) {\n                const confetti = document.createElement('div');\n                confetti.className = 'confetti';\n                confetti.style.left = Math.random() * 100 + 'vw';\n                confetti.style.animationDuration = Math.random() * 2 + 3 + 's';\n                confetti.style.backgroundColor = ['#ff0', '#f00', '#0f0', '#00f'][Math.floor(Math.random()*4)];\n                document.body.appendChild(confetti);\n                setTimeout(() => confetti.remove(), 5000);\n            }\n        }\n\n    </script>\n</body>\n</html>"
      }
    ]
  }
]