[
  {
    "id": "0gmHOvVcGDoaxEI45WEw",
    "type": "definition",
    "content": {
      "term": "Ümmü Gülsüm",
      "definition": "Hz. Osman ile evlenen iki kız kardeşten ikincisinin adı nedir?"
    },
    "courseId": "OgnmTvY8rxVpEIP45iq4",
    "unitId": "g5vZnJOuq1Bg3hSVaYGZ",
    "topicId": "z1YDBRrCZCGKowz4eKSv",
    "createdAt": {
      "_seconds": 1752034180,
      "_nanoseconds": 316000000
    }
  },
  {
    "id": "7uwEEyCwSmsLbXJz2H6C",
    "type": "sentence",
    "content": {
      "text": "Çocukların eğitimi ve hayata hazırlanması ailelerin önemli sorumlulukları arasındadır."
    },
    "courseId": "OgnmTvY8rxVpEIP45iq4",
    "unitId": "g5vZnJOuq1Bg3hSVaYGZ",
    "topicId": "z1YDBRrCZCGKowz4eKSv",
    "createdAt": {
      "_seconds": 1752034161,
      "_nanoseconds": 125000000
    }
  },
  {
    "id": "A7wfkDXUKfzfKsNsRjh3",
    "type": "sentence",
    "content": {
      "text": "Kasım, Zeynep, Rukıyye, Ümmü Gülsüm, Fatıma, Abdullah ve İbrahim Peygamberimizin çocuklarının isimleridir."
    },
    "courseId": "OgnmTvY8rxVpEIP45iq4",
    "unitId": "g5vZnJOuq1Bg3hSVaYGZ",
    "topicId": "z1YDBRrCZCGKowz4eKSv",
    "createdAt": {
      "_seconds": 1752034161,
      "_nanoseconds": 125000000
    }
  },
  {
    "id": "CAmPbuxS6ylPQxgVjIzY",
    "type": "concept",
    "content": {
      "text": "Hz. Ali"
    },
    "courseId": "OgnmTvY8rxVpEIP45iq4",
    "unitId": "g5vZnJOuq1Bg3hSVaYGZ",
    "topicId": "z1YDBRrCZCGKowz4eKSv",
    "createdAt": {
      "_seconds": 1752034161,
      "_nanoseconds": 125000000
    }
  },
  {
    "id": "DMOCOIM69PfSuxpycNsI",
    "type": "concept",
    "content": {
      "text": "Çocuk"
    },
    "courseId": "OgnmTvY8rxVpEIP45iq4",
    "unitId": "g5vZnJOuq1Bg3hSVaYGZ",
    "topicId": "z1YDBRrCZCGKowz4eKSv",
    "createdAt": {
      "_seconds": 1752034161,
      "_nanoseconds": 125000000
    }
  },
  {
    "id": "DYejFiw5GIybGG2u8aDq",
    "type": "sentence",
    "content": {
      "text": "Hz. Fatıma, Peygamberimizin en küçük kızıdır ve Peygamberimizin soyu ondan devam etmiştir."
    },
    "courseId": "OgnmTvY8rxVpEIP45iq4",
    "unitId": "g5vZnJOuq1Bg3hSVaYGZ",
    "topicId": "z1YDBRrCZCGKowz4eKSv",
    "createdAt": {
      "_seconds": 1752034161,
      "_nanoseconds": 125000000
    }
  },
  {
    "id": "GfDgTXcAk0Y3jPRFvJUe",
    "type": "definition",
    "content": {
      "term": "İbrahim",
      "definition": "Peygamberimizin Hz. Mariye'den olan oğlunun adı nedir?"
    },
    "courseId": "OgnmTvY8rxVpEIP45iq4",
    "unitId": "g5vZnJOuq1Bg3hSVaYGZ",
    "topicId": "z1YDBRrCZCGKowz4eKSv",
    "createdAt": {
      "_seconds": 1752034180,
      "_nanoseconds": 316000000
    }
  },
  {
    "id": "IhTKl9Pld20W1b5gdzWl",
    "type": "definition",
    "content": {
      "term": "Rukıyye",
      "definition": "Bedir Savaşı sırasında vefat eden Peygamberimizin kızının adı nedir?"
    },
    "courseId": "OgnmTvY8rxVpEIP45iq4",
    "unitId": "g5vZnJOuq1Bg3hSVaYGZ",
    "topicId": "z1YDBRrCZCGKowz4eKSv",
    "createdAt": {
      "_seconds": 1752034180,
      "_nanoseconds": 316000000
    }
  },
  {
    "id": "Inic8hzQvowcZyITTmfZ",
    "type": "concept",
    "content": {
      "text": "Aile"
    },
    "courseId": "OgnmTvY8rxVpEIP45iq4",
    "unitId": "g5vZnJOuq1Bg3hSVaYGZ",
    "topicId": "z1YDBRrCZCGKowz4eKSv",
    "createdAt": {
      "_seconds": 1752034161,
      "_nanoseconds": 125000000
    }
  },
  {
    "id": "MxUDbwKLPqTurvJUe3dA",
    "type": "sentence",
    "content": {
      "text": "Peygamber Efendimiz, çocuklarına değer verir, onların görüşlerini önemser ve aralarında adaletli davranırdı."
    },
    "courseId": "OgnmTvY8rxVpEIP45iq4",
    "unitId": "g5vZnJOuq1Bg3hSVaYGZ",
    "topicId": "z1YDBRrCZCGKowz4eKSv",
    "createdAt": {
      "_seconds": 1752034161,
      "_nanoseconds": 125000000
    }
  },
  {
    "id": "QckX1guuNds9PWu0YWkH",
    "type": "definition",
    "content": {
      "term": "Ali",
      "definition": "Hz. Fatıma ile evlenen kişinin adı nedir?"
    },
    "courseId": "OgnmTvY8rxVpEIP45iq4",
    "unitId": "g5vZnJOuq1Bg3hSVaYGZ",
    "topicId": "z1YDBRrCZCGKowz4eKSv",
    "createdAt": {
      "_seconds": 1752034180,
      "_nanoseconds": 316000000
    }
  },
  {
    "id": "QdO8kONOv8F6NspI1ben",
    "type": "sentence",
    "content": {
      "text": "Peygamberimizin kızı Hz. Rukıyye'nin vefatı, ailesi ve Müslümanlar için hüzünlü bir dönem olmuştur."
    },
    "courseId": "OgnmTvY8rxVpEIP45iq4",
    "unitId": "g5vZnJOuq1Bg3hSVaYGZ",
    "topicId": "z1YDBRrCZCGKowz4eKSv",
    "createdAt": {
      "_seconds": 1752034161,
      "_nanoseconds": 125000000
    }
  },
  {
    "id": "RKMOHuYVjE0PHVtdFeWL",
    "type": "sentence",
    "content": {
      "text": "Peygamber Efendimiz, Hz. Fatıma ve Hz. Ali'nin arasında arabuluculuk yaparak ailevi sorunların çözümünde yardımcı olurdu."
    },
    "courseId": "OgnmTvY8rxVpEIP45iq4",
    "unitId": "g5vZnJOuq1Bg3hSVaYGZ",
    "topicId": "z1YDBRrCZCGKowz4eKSv",
    "createdAt": {
      "_seconds": 1752034161,
      "_nanoseconds": 125000000
    }
  },
  {
    "id": "RerXha3kqUQpFjuiNWYn",
    "type": "definition",
    "content": {
      "term": "Ebülkasım",
      "definition": "Peygamberimizin ilk çocuğunun adından dolayı aldığı künye nedir?"
    },
    "courseId": "OgnmTvY8rxVpEIP45iq4",
    "unitId": "g5vZnJOuq1Bg3hSVaYGZ",
    "topicId": "z1YDBRrCZCGKowz4eKSv",
    "createdAt": {
      "_seconds": 1752034180,
      "_nanoseconds": 316000000
    }
  },
  {
    "id": "YPCers7XyF5IqhKZlpDq",
    "type": "sentence",
    "content": {
      "text": "Peygamber Efendimiz, çocuklara sevgi ve şefkatle yaklaşılması gerektiğini öğütlemiş ve bunu kendi hayatında uygulayarak Müslümanlara örnek olmuştur."
    },
    "courseId": "OgnmTvY8rxVpEIP45iq4",
    "unitId": "g5vZnJOuq1Bg3hSVaYGZ",
    "topicId": "z1YDBRrCZCGKowz4eKSv",
    "createdAt": {
      "_seconds": 1752034161,
      "_nanoseconds": 125000000
    }
  },
  {
    "id": "ZOd0GrVp0VTKhBdPLYJ1",
    "type": "concept",
    "content": {
      "text": "Eğitim"
    },
    "courseId": "OgnmTvY8rxVpEIP45iq4",
    "unitId": "g5vZnJOuq1Bg3hSVaYGZ",
    "topicId": "z1YDBRrCZCGKowz4eKSv",
    "createdAt": {
      "_seconds": 1752034161,
      "_nanoseconds": 125000000
    }
  },
  {
    "id": "atIHwaLuORzZz8ufy14Y",
    "type": "sentence",
    "content": {
      "text": "Peygamber Efendimiz, çocuklarına olan sevgisini her fırsatta gösterir ve onları korurdu."
    },
    "courseId": "OgnmTvY8rxVpEIP45iq4",
    "unitId": "g5vZnJOuq1Bg3hSVaYGZ",
    "topicId": "z1YDBRrCZCGKowz4eKSv",
    "createdAt": {
      "_seconds": 1752034161,
      "_nanoseconds": 125000000
    }
  },
  {
    "id": "ctygSDboMN4WjAeyM4hR",
    "type": "concept",
    "content": {
      "text": "Örnek Olma"
    },
    "courseId": "OgnmTvY8rxVpEIP45iq4",
    "unitId": "g5vZnJOuq1Bg3hSVaYGZ",
    "topicId": "z1YDBRrCZCGKowz4eKSv",
    "createdAt": {
      "_seconds": 1752034161,
      "_nanoseconds": 125000000
    }
  },
  {
    "id": "dXSwMKa27chVg2vRjf88",
    "type": "sentence",
    "content": {
      "text": "Peygamberimizin çocuk sevgisi, günümüzde de ebeveynler için önemli bir örnektir."
    },
    "courseId": "OgnmTvY8rxVpEIP45iq4",
    "unitId": "g5vZnJOuq1Bg3hSVaYGZ",
    "topicId": "z1YDBRrCZCGKowz4eKSv",
    "createdAt": {
      "_seconds": 1752034161,
      "_nanoseconds": 125000000
    }
  },
  {
    "id": "e9XJKRHfrOid9PDtSKiK",
    "type": "definition",
    "content": {
      "term": "Kasım",
      "definition": "Peygamberimizin ilk çocuğunun adı nedir?"
    },
    "courseId": "OgnmTvY8rxVpEIP45iq4",
    "unitId": "g5vZnJOuq1Bg3hSVaYGZ",
    "topicId": "z1YDBRrCZCGKowz4eKSv",
    "createdAt": {
      "_seconds": 1752034180,
      "_nanoseconds": 316000000
    }
  },
  {
    "id": "isr5cniuYPCfMcaq8ixe",
    "type": "concept",
    "content": {
      "text": "Hz. Fatıma"
    },
    "courseId": "OgnmTvY8rxVpEIP45iq4",
    "unitId": "g5vZnJOuq1Bg3hSVaYGZ",
    "topicId": "z1YDBRrCZCGKowz4eKSv",
    "createdAt": {
      "_seconds": 1752034161,
      "_nanoseconds": 125000000
    }
  },
  {
    "id": "kyxWEAClrNUfIss3cxc1",
    "type": "concept",
    "content": {
      "text": "Peygamber Efendimiz"
    },
    "courseId": "OgnmTvY8rxVpEIP45iq4",
    "unitId": "g5vZnJOuq1Bg3hSVaYGZ",
    "topicId": "z1YDBRrCZCGKowz4eKSv",
    "createdAt": {
      "_seconds": 1752034161,
      "_nanoseconds": 125000000
    }
  },
  {
    "id": "mCoa5n8DP7NUeMLj5NNu",
    "type": "definition",
    "content": {
      "term": "Zeyneb",
      "definition": "Peygamberimizin en büyük kızının adı nedir?"
    },
    "courseId": "OgnmTvY8rxVpEIP45iq4",
    "unitId": "g5vZnJOuq1Bg3hSVaYGZ",
    "topicId": "z1YDBRrCZCGKowz4eKSv",
    "createdAt": {
      "_seconds": 1752034180,
      "_nanoseconds": 316000000
    }
  },
  {
    "id": "mVEpKsaoYQs4OtRbYXiS",
    "type": "sentence",
    "content": {
      "text": "Hz. Ali, Peygamberimizin damadı ve önemli bir sahabesidir."
    },
    "courseId": "OgnmTvY8rxVpEIP45iq4",
    "unitId": "g5vZnJOuq1Bg3hSVaYGZ",
    "topicId": "z1YDBRrCZCGKowz4eKSv",
    "createdAt": {
      "_seconds": 1752034161,
      "_nanoseconds": 125000000
    }
  },
  {
    "id": "myQpZziabqXvo0h39GzR",
    "type": "concept",
    "content": {
      "text": "Sevgi ve Şefkat"
    },
    "courseId": "OgnmTvY8rxVpEIP45iq4",
    "unitId": "g5vZnJOuq1Bg3hSVaYGZ",
    "topicId": "z1YDBRrCZCGKowz4eKSv",
    "createdAt": {
      "_seconds": 1752034161,
      "_nanoseconds": 125000000
    }
  },
  {
    "id": "poIJXBEZLycJYDHU4wJ0",
    "type": "definition",
    "content": {
      "term": "Fatıma",
      "definition": "Peygamberimizin soyunun devam ettiği kızının adı nedir?"
    },
    "courseId": "OgnmTvY8rxVpEIP45iq4",
    "unitId": "g5vZnJOuq1Bg3hSVaYGZ",
    "topicId": "z1YDBRrCZCGKowz4eKSv",
    "createdAt": {
      "_seconds": 1752034180,
      "_nanoseconds": 316000000
    }
  },
  {
    "id": "yzV3gUNGcPjaBPmEhFd1",
    "type": "concept",
    "content": {
      "text": "Sorumluluk"
    },
    "courseId": "OgnmTvY8rxVpEIP45iq4",
    "unitId": "g5vZnJOuq1Bg3hSVaYGZ",
    "topicId": "z1YDBRrCZCGKowz4eKSv",
    "createdAt": {
      "_seconds": 1752034161,
      "_nanoseconds": 125000000
    }
  },
  {
    "id": "ztNZlPHpkjfoypwLoxnP",
    "type": "concept",
    "content": {
      "text": "Medine"
    },
    "courseId": "OgnmTvY8rxVpEIP45iq4",
    "unitId": "g5vZnJOuq1Bg3hSVaYGZ",
    "topicId": "z1YDBRrCZCGKowz4eKSv",
    "createdAt": {
      "_seconds": 1752034161,
      "_nanoseconds": 125000000
    }
  }
]